Workbook
Name _bookmark28: Guidance!$B$43
Name _bookmark32: Guidance!$B$44
Name _Toc112658799: Guidance!#REF!
Name _Toc112658800: Guidance!$B$15
Name _Toc112658801: Guidance!$B$16
Name _Toc112658802: Guidance!$B$20
Name _Toc112658803: Guidance!$B$23
Name _Toc112658804: Guidance!$B$27
Name _Toc112658805: Guidance!$B$41
Name _Toc112658807: Guidance!$B$60
Name _Toc112671323: Guidance!$B$2
Name _Toc112671324: Guidance!$B$3
Name _Toc50979603: 'Building Register'!$A$1
Name _Toc50979604: 'Intangible Asset Register '!$A$1
Name _Toc50979605: 'Stocks Consumables Register '!#REF!
Name _Toc50979606: 'Railway register '!$A$1
Name _Toc50979607: 'Roads Infastructure register '!$A$1
Name _Toc50979608: 'Other Infastructure register '!$A$1
Name _Toc50979609: 'Biological register '!$A$1
Name _Toc50979610: 'Subsoil register '!$A$1
Name _Toc50979611: 'Major maintenance register '!$A$1
Name _Toc50979612: 'Work in progress register '!$A$1
Name _Toc50979614: 'Cash register '!$A$1
Name _Toc50979615: 'Bank register '!$A$1
Name _Toc50979616: 'Loans receivables register'!$A$1
Name _Toc50979617: 'Accounts receivables register '!$A$1
Name _Toc50979618: 'Other receivables register '!$A$1
Name _Toc50979619: 'Imprest register '!$A$1
Name _Toc50979620: 'Loans payable register '!$A$1
Name _Toc50979621: 'contigent Liabities register'!$A$1
Name _Toc50979622: 'Accruals register '!$A$1
Name _Toc50979623: 'Accounts payable register '!$A$1
Name _Toc50979624: 'Pensions payable register'!$A$1
Name _Toc50979625: 'Other liabilities register '!$A$1
Name _Toc50979626: 'Asset movement form'!$A$1
Name _Toc50979627: 'Revaluation Schedule '!$A$1
Name _Toc50979628: 'Losses Register '!$A$1
Name _Toc50979629: 'Guarantees &indeminities '!$A$1
Name _Toc50979630: 'Lease register '!$A$1
Name _Toc50979631: 'Litigation Register '!$A$2
Name _Toc50979632: 'Equipment sign out register '!$A$1
Name _Toc50979633: 'Asset transfer form '!$A$1
Name _Toc50979634: 'Asset Handover form'!$A$1
Name _Toc50979635: 'Asset reconciliation report '!$A$1

Sheet Guidance
B2: ASSET AND LIABLILITY REPORTING TEMPLATES
B4: General
B5: Mode of acquisition - mode of acquisition may be through purchase, transfer, donation etc
B8: Land register
B9: Polygon under the land register refers to the GPS readings of the four corners of a plot of land
B10: Encumbrances under the land register refers to any caveats placed on a plot of land
B11: Planned / unplanned in the land register refers to whether the plot of land is located in an area that has formal plans or otherwise
B13: Intangible assets
B14: Intangible assets - Documents of ownership include copyrights, patents for intellectual property; also special access rights for software
B16: 1.All Accounting officers are supposed to ensure that their entity has documents of ownership for its property. Where an entity is a body corporate, the documents of ownership should be in the name of the entity and under the custody of the Accounting Officer
B17: 2.All MDAs are required to submit quarterly and annual reports to The National Treasury & Planning using the prescribed format.
B18: 3.Public Sector entities will be required to submit their Quaterly reports for asset management structures, ownership documents and asset registers should be submitted quarterly by 15th of the subsequent month after every quarter. and annual disposal plans by 15th of October of the financial year.

Sheet Table of Contents
A1: Guidance
A2: Table of Contents
A3: Land Register
A4: Building Register
A5: Motor Vehicle Register
A6: Office equipment register
A7: ICT Computer Register
A8: Furniture&Fittings
A9: Plant &Machinery Register
A10: Portable &attractive Items
A11: Intangible Asset Register
A12: Stocks Consumables Register
... A42: Asset reconciliation report

Sheet Land Register 
A1: Land Register | B1: Land Register
A2: Description of land | B2: Mode of Acquisition e.g. purchase, transfer, donation etc. | C2: Category (Land or investment property) | D2: County | E2: Nearest town/ Location | F2: GPS | G2: Polygon* | K2: L.R /certifcate No. Or other unique identifier | L2: Document of ownership held (Title deed, certificate, allotment letter, etc.) | M2: Proprietorship/ ownership details as per document of title | N2: Size (ha) | O2: Ownership status (Freehold /leasehold) | P2: Acquisition date | Q2: Registration date | R2: Disputed/ undisputed | S2: Encumberances | T2: Planned/ Unplanned | U2: Purpose/ Use of land | V2: Surveyed/ Not surveyed | W2: Acquisition Amount | X2: Fair value/ Ministry of Lands zonal maps or land index | Y2: Disposal date/ Change of use date | Z2: Disposal value | AA2: Annual rental income (for investment property) | AB2: Remarks
G3: A | H3: B | I3: C | J3: D
A4: None | B4: None | C4: None | D4: None | E4: None | F4: None | G4: None | H4: None | I4: None | J4: None | K4: None | L4: None | M4: None | N4: None | O4: None | P4: None | Q4: None | R4: None | S4: None | T4: None | U4: None | V4: None | W4: None | X4: None
A10: Prepared by: Doris Muthini Designation: Manager SCM Date: 30th June 2025
A11: Checked by: David NjaneDesignation: Finance Manager Date: 30th June 2025
A12: Authorized by: Dr. Laxmana P. Kiptoo Designation: Director/Chief Executive Officer Date: 30th June 2025

Sheet Building Register
A1: Buildings Register
B2: Description/ Name of building | C2: Building ownership | D2: Category (Building or investment property) | E2: Building No. | F2: Institution No. | G2: Nearest town/ Shopping centre | H2: Street | I2: County | J2: L.R N o. | K2: Size of land (ha) | L2: Ownership status (Freehold/ leasehold) | M2: Source of funds | N2: Mode of acquisition | O2: Date of purchase/ Building commisssioning (for constructed buildings) | P2: Type of building (Permanent/ temporary) | Q2: Designated use | R2: Estimated useful life | S2: No. of floors | T2: Plinth Area | U2: Cost of construction/ Valuation | V2: Annual depreciation | W2: Estimated useful life | X2: Accumulated depreciation to date | Y2: Net Book value | Z2: Annual rental income (for investment property) | AA2: Remarks
A3: 1 | B3: None | C3: None | D3: None | E3: None | F3: None | G3: None | H3: None | I3: None | J3: None | K3: None | L3: None | M3: None | N3: None | O3: None | P3: None | Q3: None | R3: None | S3: None | T3: None | U3: None | V3: None | W3: None | X3: None | Y3: None | Z3: None
A4: 2
A5: 3
A6: 4
A7: 5
A10: Prepared by: Doris Muthini Designation: Manager SCM Date: 30th June 2025
A11: Checked by: David NjaneDesignation: Finance Manager Date: 30th June 2025
A12: Authorized by: Dr. Laxmana P. Kiptoo Designation: Director/Chief Executive Officer Date: 30th June 2025

Sheet Motor Vehicle Register
A1: Motor vehicle Register
A2: No. | B2: Vehicle Registration No. | C2: Financed by/ source of funds | D2: Engine No. | E2: Chassis No. | F2: Tag number/ | G2: Make & Model | H2: Year of purchase | I2: PV number | J2: Original Location | K2: Current Location | L2: Replacement Date (if applicable) | M2: Amount | N2: Depreciation rate | O2: Annual depreciation | P2: Accumulated depreciation | Q2: Net Book Value | R2: Date of disposal | S2: Disposal value | T2: Responsible officer | U2: Asset condition | V2: Does the MV have a log book(Y/N) | W2: Notes
A3: 1 | B3: KCT 857Y | C3: GOK | D3: CNF097931 | E3: WV1ZZZ2HZJA041835 | F3: NGOB/04/0002 | G3: Volkswagen Amarok DC 4x4 MT 103 Comfortline | H3: 2020 | I3: 18/20/21 | J3: Nairobi | K3: Nairobi | L3: 2029 | M3: 6655350 | N3: 0.25 | O3: =P3/(2025-H3) -> 1015200.9 | P3: =M3-Q3 -> 5076004.3 | Q3: =M3*(1-N3)^(2025-H3) -> 1579345.8 | R3: 2033 | T3: Senior Officer Administration | U3: Good | V3: Y
A4: 2 | B4: KCT 859Y | C4: GOK | D4: CNF1121315 | E4: WV1ZZZ2HZKA041160 | F4: NGOB/04/0003 | G4: Volkswagen Amarok DC 4x4 MT 103 Comfortline | H4: 2020 | I4: 18/20/21 | J4: Nairobi | K4: Nairobi | L4: 2029 | M4: 6655350 | N4: 0.25 | O4: =P4/(2025-H4) -> 1015200.9 | P4: =M4-Q4 -> 5076004.3 | Q4: =M4*(1-N4)^(2025-H4) -> 1579345.8 | R4: 2033 | T4: Senior Officer Administration | U4: Good | V4: Y
A5: 3 | B5: KCT 856Y | C5: GOK | D5: CNF112493 | E5: WV1ZZZ2HZKAO40798 | F5: NGOB/04/0004 | G5: Volkswagen Amarok DC 4x4 MT 103 Comfortline | H5: 2020 | I5: 18/20/21 | J5: Nairobi | K5: Nairobi | L5: 2029 | M5: 6655350 | N5: 0.25 | O5: =P5/(2025-H5) -> 1015200.9 | P5: =M5-Q5 -> 5076004.3 | Q5: =M5*(1-N5)^(2025-H5) -> 1579345.8 | R5: 2033 | T5: Senior Officer Administration | U5: Good | V5: Y
A6: 4 | B6: KCT 858Y | C6: GOK | D6: CNF111885 | E6: WV1ZZZ2HZKA039232 | F6: NGOB/04/0001 | G6: Volkswagen Amarok DC 4x4 MT 103 Comfortline | H6: 2020 | I6: 18/20/21 | J6: Nairobi | K6: Nairobi | L6: 2029 | M6: 6655350 | N6: 0.25 | O6: =P6/(2025-H6) -> 1015200.9 | P6: =M6-Q6 -> 5076004.3 | Q6: =M6*(1-N6)^(2025-H6) -> 1579345.8 | R6: 2033 | T6: Senior Officer Administration | U6: Good | V6: Y
A7: 5 | B7: KCT 885Y | C7: GOK | D7: 1KDB051337 | E7: JTEBH3FJ70K229360 | F7: NGOB/04/0005 | G7: 3.0 L/Cruiser Prado KDJI50R-GKAEY | H7: 2020 | I7: 19/20/21 | J7: Nairobi | K7: Nairobi | L7: 2029 | M7: 10977414 | N7: 0.25 | O7: =P7/(2025-H7) -> 1674484.4 | P7: =M7-Q7 -> 8372422.2 | Q7: =M7*(1-N7)^(2025-H7) -> 2604991.8 | R7: 2033 | T7: Senior Officer Administration | U7: Good | V7: Y
A8: 6 | B8: KCT 903Y | C8: GOK | D8: 1KD-B043708 | E8: JTEBH3FJ20K227788 | F8: NGOB/04/0006 | G8: 3.0 L/Cruiser Prado KDJI50R-GKAEY | H8: 2020 | I8: 20/20/21 | J8: Nairobi | K8: Nairobi | L8: 2029 | M8: 10977414 | N8: 0.25 | O8: =P8/(2025-H8) -> 1674484.4 | P8: =M8-Q8 -> 8372422.2 | Q8: =M8*(1-N8)^(2025-H8) -> 2604991.8 | R8: 2033 | T8: Senior Officer Administration | U8: Good | V8: Y
A9: 7 | B9: KCT 853Y | C9: GOK | D9: CNF097931 | E9: WVIZZZ2HZJA041835 | F9: NGOB/04/0007 | G9: Toyota Rush F800RE-GQGF | H9: 2020 | I9: 21/20/21 | J9: Nairobi | K9: Nairobi | L9: 2029 | M9: 3555621 | N9: 0.25 | O9: =P9/(2025-H9) -> 542371.09 | P9: =M9-Q9 -> 2711855.5 | Q9: =M9*(1-N9)^(2025-H9) -> 843765.53 | R9: 2033 | T9: Senior Officer Administration | U9: Good | V9: Y
A10: 8 | B10: KCT 844Y | C10: GOK | D10: 2KD-B026547 | E10: JTFSS22P900188937 | F10: NGOB/04/0008 | G10: Hiace Mini bus KDH222R-LEMDY | H10: 2020 | I10: 22/20/21 | J10: Nairobi | K10: Nairobi | L10: 2029 | M10: 5218448 | N10: 0.25 | O10: =P10/(2025-H10) -> 796017.17 | P10: =M10-Q10 -> 3980085.8 | Q10: =M10*(1-N10)^(2025-H10) -> 1238362.2 | R10: 2033 | T10: Senior Officer Administration | U10: Good | V10: Y
M11: =SUM(M3:M10) -> 57350297 | O11: =SUM(O3:O10) -> 8748160.5 | P11: =SUM(P3:P10) -> 43740803 | Q11: =SUM(Q3:Q10) -> 13609494
A13: Prepared by: Doris Muthini Designation: Manager SCM Date: 30th June 2025
A14: Checked by: David NjaneDesignation: Finance Manager Date: 30th June 2025
A15: Authorized by: Dr. Laxmana P. Kiptoo Designation: Director/Chief Executive Officer Date: 30th June 2025

Sheet Office equipment register 
A1: Asset Description | B1: Financed by/ source of funds | C1: Serial number | D1: Tag number | E1: Make & Model | F1: Date of Delivery / installation | G1: PV number | H1: Original Location | I1: Current Location | J1: Replacement Date (if applicable) | K1: Purchase amount | L1: 0.125 | M1: Annual depreciation | N1: Accumulated depreciation | O1: Net Book Value | P1: Date of disposal | Q1: Disposal value | R1: Responsible officer | S1: Asset condition | T1: Notes
A2: TYPE WRITER | B2: GOK | C2: N/A | D2: NGOB/03/0092 | E2: IBM Wheel writer 50 Series | F2: 2017 | H2: Nairobi | I2: Nairobi | J2: 2023 | K2: 137500 | L2: 0.125 | M2: =N2/(2025-F2) -> 11281.722 | N2: =K2-O2 -> 90253.774 | O2: =K2*(1-L2)^(2025-F2) -> 47246.226 | R2: Margret Mwai | S2: Good | T2: In Use
A3: SERVER | B3: GOK | C3: B1WYT2 | D3: NGOB/03/0081 | E3: POWER EDGE 2950,QUAD CORE, 32GB,600GB | F3: 2008 | H3: Nairobi | I3: Nairobi | J3: 2023 | K3: 108936 | L3: 0.125 | M3: =N3/(2025-F3) -> 5745.9978 | N3: =K3-O3 -> 97681.963 | O3: =K3*(1-L3)^(2025-F3) -> 11254.037 | R3: Admistration Officer | S3: Good | T3: In Use
A4: SERVER | B4: GOK | C4: J308EM3 | D4: NGOB/03/0083 | E4: IBM Lenovo, 8 core 3.5Ghz x2, 146GB, 6TB | F4: 2016 | H4: Nairobi | I4: Nairobi | J4: 2023 | K4: 3701817 | L4: 0.125 | M4: =N4/(2025-F4) -> 287648.54 | N4: =K4-O4 -> 2588836.8 | O4: =K4*(1-L4)^(2025-F4) -> 1112980.2 | R4: Admistration Officer | S4: Good | T4: In Use
A5: FRIDGE | B5: GOK | D5: NGOB/03/0125 | E5: Internet cabinet | H5: Kisumu | I5: Kisumu | K5: 26000 | L5: 0.125 | M5: =N5/(2025-F5) -> 12.839506 | N5: =K5-O5 -> 26000 | O5: =K5*(1-L5)^(2025-F5) -> 9.5781298e-114 | R5: Admistration Officer | S5: Good | T5: In Use
A6: Internet cabinet | B6: GOK | D6: NGOB/03/0107 | E6: Internet cabinet | H6: Kisumu | I6: Kisumu | K6: 26000 | L6: 0.125 | M6: =N6/(2025-F6) -> 12.839506 | N6: =K6-O6 -> 26000 | O6: =K6*(1-L6)^(2025-F6) -> 9.5781298e-114 | R6: Admistration Officer | S6: Good | T6: In Use
A7: SERVER | B7: GOK | C7: CKDTD5J | D7: NGOB/03/0082 | E7: POWER EDGE R710,QUAD CORE, 192GB, 1.5TB | F7: 2012 | H7: Nairobi | I7: Nairobi | J7: 2023 | K7: 1470874 | L7: 0.125 | M7: =N7/(2025-F7) -> 93203.619 | N7: =K7-O7 -> 1211647 | O7: =K7*(1-L7)^(2025-F7) -> 259226.96 | R7: Admistration Officer | S7: Good | T7: In Use
A8: SERVER | B8: GOK | C8: CZ21110271 | D8: NGOB/03/0042 | E8: HP Proliant DL380 Gen10 | F8: 2021 | H8: Nairobi | I8: Nairobi | J8: 2024 | K8: 4630000 | L8: 0.125 | M8: =N8/(2025-F8) -> 478994.75 | N8: =K8-O8 -> 1915979 | O8: =K8*(1-L8)^(2025-F8) -> 2714021 | R8: Admistration Officer | S8: Good | T8: In Use
A9: SERVER | B9: GOK | C9: CZ21110255 | D9: NGOB/03/0223 | E9: HP Proliant DL380 Gen10 | F9: 2021 | H9: Nairobi | I9: Nairobi | J9: 2024 | K9: 4630000 | L9: 0.125 | M9: =N9/(2025-F9) -> 478994.75 | N9: =K9-O9 -> 1915979 | O9: =K9*(1-L9)^(2025-F9) -> 2714021 | R9: Admistration Officer | S9: Good | T9: In Use
A10: ROUTER | B10: GOK | C10: C6910CD3D8E6/017/r2 | D10: NGOB/03/0078 | E10: Mikrotik RB201 | F10: 2021 | H10: Nairobi | I10: Nairobi | J10: 2024 | K10: 147168 | L10: 0.125 | M10: =N10/(2025-F10) -> 15225.205 | N10: =K10-O10 -> 60900.82 | O10: =K10*(1-L10)^(2025-F10) -> 86267.18 | R10: Admistration Officer | S10: Good | T10: In Use
A11: LAN installation | B11: GOK | C11: N/A | E11: Network Cabling Installation and Commissioning | F11: 2021 | H11: Nairobi | I11: Nairobi | J11: 2024 | K11: 7243896 | L11: 0.125 | M11: =N11/(2025-F11) -> 749414.29 | N11: =K11-O11 -> 2997657.2 | O11: =K11*(1-L11)^(2025-F11) -> 4246238.8 | R11: Admistration Officer | S11: Good | T11: In Use
A12: Internet cabinet | B12: GOK | C12: N/A | D12: NGOB/03/00100 | E12: Internet cabinet | F12: 2021 | H12: Mombasa | I12: Mombasa | J12: 2024 | K12: 26000 | L12: 0.125 | M12: =N12/(2025-F12) -> 2689.8193 | N12: =K12-O12 -> 10759.277 | O12: =K12*(1-L12)^(2025-F12) -> 15240.723 | R12: Admistration Officer | S12: Good | T12: In Use
A13: Internet cabinet | B13: GOK | C13: N/A | D13: NGOB/03/0114 | E13: Internet cabinet | F13: 2021 | H13: Nakuru | I13: Nakuru | J13: 2024 | K13: 26000 | L13: 0.125 | M13: =N13/(2025-F13) -> 2689.8193 | N13: =K13-O13 -> 10759.277 | O13: =K13*(1-L13)^(2025-F13) -> 15240.723 | R13: Admistration Officer | S13: Good | T13: In Use
A14: Microwave | B14: GOK | C14: N/A | D14: NGOB/03/0072 | E14: Microwave | F14: 2021 | H14: Mombasa | I14: Mombasa | J14: 2024 | K14: 18000 | L14: 0.125 | M14: =N14/(2025-F14) -> 1862.1826 | N14: =K14-O14 -> 7448.7305 | O14: =K14*(1-L14)^(2025-F14) -> 10551.27 | R14: Admistration Officer | S14: Good | T14: In Use
A15: Water dispenser | B15: GOK | C15: N/A | D15: NGOB/03/0062 | E15: Water dispensor | F15: 2021 | H15: Garisa | I15: Garisa | J15: 2021 | K15: 27675 | L15: 0.125 | M15: =N15/(2025-F15) -> 2863.1058 | N15: =K15-O15 -> 11452.423 | O15: =K15*(1-L15)^(2025-F15) -> 16222.577 | R15: Admistration Officer | S15: Good | T15: In Use
A16: Water dispenser | B16: GOK | C16: N/A | D16: NGOB/03/0108 | E16: Water dispensor | F16: 2021 | H16: Eldoret | I16: Eldoret | J16: 2021 | K16: 27675 | L16: 0.125 | M16: =N16/(2025-F16) -> 2863.1058 | N16: =K16-O16 -> 11452.423 | O16: =K16*(1-L16)^(2025-F16) -> 16222.577 | R16: Admistration Officer | S16: Good | T16: In Use
A17: Dispencer | B17: GOK | C17: N/A | D17: NGOB/03/0101 | E17: Water dispensor | F17: 2021 | H17: Kisumu | I17: Kisumu | J17: 2021 | K17: 27675 | L17: 0.125 | M17: =N17/(2025-F17) -> 2863.1058 | N17: =K17-O17 -> 11452.423 | O17: =K17*(1-L17)^(2025-F17) -> 16222.577 | R17: Admistration Officer | S17: Good | T17: In Use
A18: Bulk fillin system | C18: N/A | D18: NGOB/01/096 | E18: Bulky filling system | F18: 2014 | H18: Nairobi | I18: Nairobi | K18: 816000 | L18: 0.125 | M18: =N18/(2025-F18) -> 57105.822 | N18: =K18-O18 -> 628164.04 | O18: =K18*(1-L18)^(2025-F18) -> 187835.96 | R18: Charles Mugo | S18: Good | T18: In Use
A19: Bulk fillin system | C19: N/A | D19: NGOB/01/0086-0090 | E19: Bulky filling system | F19: 2020 | H19: Nairobi | I19: Nairobi | K19: 2837161 | L19: 0.125 | M19: =N19/(2025-F19) -> 276391.15 | N19: =K19-O19 -> 1381955.8 | O19: =K19*(1-L19)^(2025-F19) -> 1455205.2 | R19: Charles Mugo | S19: Good | T19: In Use
A20: Office Safe | B20: GOK | C20: N/A | D20: NGOB/03/0093 | E20: Office Safe | F20: 2021 | H20: Nairobi | I20: Nairobi | K20: 90000 | L20: 0.125 | M20: =N20/(2025-F20) -> 9310.9131 | N20: =K20-O20 -> 37243.652 | O20: =K20*(1-L20)^(2025-F20) -> 52756.348 | R20: Dorris Muthini | S20: Good | T20: In Use
A21: Office Safe | E21: Office Safe | F21: 2021 | H21: Nairobi | I21: Nairobi | K21: 90000 | L21: 0.125 | M21: =N21/(2025-F21) -> 9310.9131 | N21: =K21-O21 -> 37243.652 | O21: =K21*(1-L21)^(2025-F21) -> 52756.348 | R21: Muktar Mohammed | S21: Good | T21: In Use
A22: Filling cabinets | B22: GOK | C22: N/A | D22: NGOB/01/0289 | E22: Mettalic 4 drawer cabinet | F22: 2021 | H22: Nairobi | I22: Nairobi | K22: 29450 | L22: 0.125 | M22: =N22/(2025-F22) -> 3046.7377 | N22: =K22-O22 -> 12186.951 | O22: =K22*(1-L22)^(2025-F22) -> 17263.049 | R22: Elizabeth Kamau | S22: Good | T22: In Use
A23: Filling cabinets | B23: GOK | C23: N/A | D23: NGOB/01/0336 | E23: Mettalic 4 drawer cabinet | F23: 2021 | H23: Nairobi | I23: Nairobi | K23: 34162 | L23: 0.125 | M23: =N23/(2025-F23) -> 3534.2157 | N23: =K23-O23 -> 14136.863 | O23: =K23*(1-L23)^(2025-F23) -> 20025.137 | R23: Arasa Mokuah | S23: Good | T23: In Use
A24: Filling cabinets | B24: GOK | C24: N/A | D24: NGOB/01/0331 | E24: Mettalic double door | F24: 2021 | H24: Nairobi | I24: Nairobi | K24: 34162 | L24: 0.125 | M24: =N24/(2025-F24) -> 3534.2157 | N24: =K24-O24 -> 14136.863 | O24: =K24*(1-L24)^(2025-F24) -> 20025.137 | R24: Dorris Muthini | S24: Good | T24: In Use
A25: Filling cabinets | B25: GOK | C25: N/A | D25: NGOB/01/0133 | E25: Mettalic 4 drawer cabinet | F25: 2021 | H25: Nairobi | I25: Nairobi | K25: 29450 | L25: 0.125 | M25: =N25/(2025-F25) -> 3046.7377 | N25: =K25-O25 -> 12186.951 | O25: =K25*(1-L25)^(2025-F25) -> 17263.049 | R25: Beatrice Topisa | S25: Good | T25: In Use
A26: Filling cabinets | B26: GOK | C26: N/A | D26: NGOB/01/0313 | E26: Mettalic 4 drawer cabinet | F26: 2021 | H26: Nairobi | I26: Nairobi | K26: 34162 | L26: 0.125 | M26: =N26/(2025-F26) -> 3534.2157 | N26: =K26-O26 -> 14136.863 | O26: =K26*(1-L26)^(2025-F26) -> 20025.137 | R26: Berly Odete | S26: Good | T26: In Use
A27: Filling cabinets | B27: GOK | C27: N/A | D27: NGOB/01/0314 | E27: Mettalic 4 drawer cabinet | F27: 2021 | H27: Nairobi | I27: Nairobi | K27: 34162 | L27: 0.125 | M27: =N27/(2025-F27) -> 3534.2157 | N27: =K27-O27 -> 14136.863 | O27: =K27*(1-L27)^(2025-F27) -> 20025.137 | R27: Berly Odete | S27: Good | T27: In Use
A28: Filling cabinets | B28: GOK | C28: N/A | D28: NGOB/01/0315 | E28: Mettalic 4 drawer cabinet | F28: 2021 | H28: Nairobi | I28: Nairobi | K28: 34162 | L28: 0.125 | M28: =N28/(2025-F28) -> 3534.2157 | N28: =K28-O28 -> 14136.863 | O28: =K28*(1-L28)^(2025-F28) -> 20025.137 | R28: Berly Odete | S28: Good | T28: In Use
A29: Filling cabinets | B29: GOK | C29: N/A | D29: NGOB/01/0434 | E29: Mettalic 4 drawer cabinet | F29: 2021 | H29: Nairobi | I29: Nairobi | K29: 34162 | L29: 0.125 | M29: =N29/(2025-F29) -> 3534.2157 | N29: =K29-O29 -> 14136.863 | O29: =K29*(1-L29)^(2025-F29) -> 20025.137 | R29: Isaiah Sang | S29: Good | T29: In Use
A30: Filling cabinets | B30: GOK | C30: N/A | D30: NGOB/01/0389 | E30: Mettalic 4 drawer cabinet | F30: 2021 | H30: Nairobi | I30: Nairobi | K30: 34162 | L30: 0.125 | M30: =N30/(2025-F30) -> 3534.2157 | N30: =K30-O30 -> 14136.863 | O30: =K30*(1-L30)^(2025-F30) -> 20025.137 | R30: Judy Njiru | S30: Good | T30: In Use
A31: Filling cabinets | B31: GOK | C31: N/A | D31: NGOB/01/0379 | E31: Mettalic 4 drawer cabinet | F31: 2021 | H31: Nairobi | I31: Nairobi | K31: 29450 | L31: 0.125 | M31: =N31/(2025-F31) -> 3046.7377 | N31: =K31-O31 -> 12186.951 | O31: =K31*(1-L31)^(2025-F31) -> 17263.049 | R31: Ephy Nafuna | S31: Good | T31: In Use
A32: Filling cabinets | B32: GOK | C32: N/A | D32: NGOB/01/0378 | E32: Mettalic 4 drawer cabinet | F32: 2021 | H32: Nairobi | I32: Nairobi | K32: 29450 | L32: 0.125 | M32: =N32/(2025-F32) -> 3046.7377 | N32: =K32-O32 -> 12186.951 | O32: =K32*(1-L32)^(2025-F32) -> 17263.049 | R32: Ephy Nafuna | S32: Good | T32: In Use
A33: Filling cabinets | B33: GOK | C33: N/A | D33: NGOB/01/0150 | E33: Mettalic 4 drawer cabinet | F33: 2021 | H33: Nairobi | I33: Nairobi | K33: 34162 | L33: 0.125 | M33: =N33/(2025-F33) -> 3534.2157 | N33: =K33-O33 -> 14136.863 | O33: =K33*(1-L33)^(2025-F33) -> 20025.137 | R33: Ephy Nafuna | S33: Good | T33: In Use
... A48: Water dispenser | B48: GOK | C48: N/A | D48: NGOB/03/0066 | E48: Water dispenser | F48: 2021 | H48: Nairobi | I48: Nairobi | K48: 32099 | L48: 0.125 | M48: =N48/(2025-F48) -> 3320.7889 | N48: =K48-O48 -> 13283.156 | O48: =K48*(1-L48)^(2025-F48) -> 18815.844 | R48: Elizabeth Kamau | S48: Good | T48: In Use
A49: Water dispenser | B49: GOK | C49: N/A | D49: NGOB/03/0016 | E49: Water dispenser | F49: 2021 | H49: Nairobi | I49: Nairobi | K49: 32099 | L49: 0.125 | M49: =N49/(2025-F49) -> 3320.7889 | N49: =K49-O49 -> 13283.156 | O49: =K49*(1-L49)^(2025-F49) -> 18815.844 | R49: Elizabeth Kamau | T49: In Use
A50: Water dispenser | B50: GOK | C50: N/A | E50: Water dispenser | F50: 2023 | H50: Nairobi | I50: Nairobi | K50: 16495 | L50: 0.125 | M50: =N50/(2025-F50) -> 1933.0078 | N50: =K50-O50 -> 3866.0156 | O50: =K50*(1-L50)^(2025-F50) -> 12628.984 | R50: Elizabeth Kamau | T50: In Use
A51: Water dispenser | B51: GOK | C51: N/A | E51: Water dispensor | F51: 2021 | H51: Nairobi | I51: Nairobi | K51: 16495 | L51: 0.125 | M51: =N51/(2025-F51) -> 1706.4835 | N51: =K51-O51 -> 6825.9338 | O51: =K51*(1-L51)^(2025-F51) -> 9669.0662 | R51: Elizabeth Kamau | S51: Good | T51: In Use
A52: Office equipments | B52: GOK | D52: NGOB/01/0230 | E52: Metal cabinet | F52: 2016 | H52: Eldoret | I52: Eldoret | K52: 22285 | L52: 0.125 | M52: =N52/(2025-F52) -> 1731.649 | N52: =K52-O52 -> 15584.841 | O52: =K52*(1-L52)^(2025-F52) -> 6700.1591 | R52: Carolyne Kimaiyo | S52: Good | T52: In Use
A53: Office equipments | B53: GOK | D53: NGOB/01/0231 | E53: Metal cabinet | F53: 2016 | H53: Eldoret | I53: Eldoret | K53: 22285 | L53: 0.125 | M53: =N53/(2025-F53) -> 1731.649 | N53: =K53-O53 -> 15584.841 | O53: =K53*(1-L53)^(2025-F53) -> 6700.1591 | R53: Carolyne Kimaiyo | S53: Good | T53: In Use
A54: Office equipments | B54: GOK | D54: NGOB/01/0232 | E54: Metal cabinet | F54: 2021 | H54: Eldoret | I54: Eldoret | K54: 34162 | L54: 0.125 | M54: =N54/(2025-F54) -> 3534.2157 | N54: =K54-O54 -> 14136.863 | O54: =K54*(1-L54)^(2025-F54) -> 20025.137 | R54: Carolyne Kimaiyo | S54: Good | T54: In Use
A55: OFFICE CARPET | E55: Office Carpet | F55: 2016 | H55: NRB | I55: NRB | K55: 1410000 | L55: 0.125 | M55: =N55/(2025-F55) -> 109563.61 | N55: =K55-O55 -> 986072.5 | O55: =K55*(1-L55)^(2025-F55) -> 423927.5 | R55: Ephy Nafuna | T55: In Use
A56: Office equipments | B56: GOK | D56: NGOB/01/0157 | E56: Cabinets | F56: 2016 | H56: Garisa | I56: Garisa | K56: 22285 | L56: 0.125 | M56: =N56/(2025-F56) -> 1731.649 | N56: =K56-O56 -> 15584.841 | O56: =K56*(1-L56)^(2025-F56) -> 6700.1591 | R56: Joseph Kaluu | T56: In Use
A57: Office equipments | B57: GOK | D57: NGOB/01/0158 | E57: Cabinets | F57: 2021 | H57: Garisa | I57: Garisa | K57: 34162 | L57: 0.125 | M57: =N57/(2025-F57) -> 3534.2157 | N57: =K57-O57 -> 14136.863 | O57: =K57*(1-L57)^(2025-F57) -> 20025.137 | R57: Joseph Kaluu | T57: In Use
A58: Office equipments | B58: GOK | D58: NGOB/01/331 | E58: Metallic cabinet -2 door | F58: 2020 | H58: Nairobi | I58: Nairobi | J58: 2029 | K58: 34320 | L58: 0.125 | M58: =N58/(2025-F58) -> 3343.3931 | N58: =K58-O58 -> 16716.965 | O58: =K58*(1-L58)^(2025-F58) -> 17603.035 | R58: Doris Muthini | T58: In Use
A59: Office equipments | B59: GOK | D59: NGOB/1/0289 | E59: Metallic cabinet -2 door | F59: 2020 | H59: Nairobi | I59: Nairobi | J59: 2029 | K59: 34320 | L59: 0.125 | M59: =N59/(2025-F59) -> 3343.3931 | N59: =K59-O59 -> 16716.965 | O59: =K59*(1-L59)^(2025-F59) -> 17603.035 | R59: Elizabeth Kamau | T59: In Use
A60: Office equipments | B60: GOK | D60: NGOB/01/0133 | E60: Metallic cabinet - 4 door | F60: 2020 | H60: Nairobi | I60: Nairobi | J60: 2029 | K60: 31540 | L60: 0.125 | M60: =N60/(2025-F60) -> 3072.5704 | N60: =K60-O60 -> 15362.852 | O60: =K60*(1-L60)^(2025-F60) -> 16177.148 | R60: Beatrice Topisa | T60: In Use
A61: Office equipments | B61: GOK | E61: Metallic cabinet - 4 door | F61: 2020 | H61: Nairobi | I61: Nairobi | J61: 2029 | K61: 31540 | L61: 0.125 | M61: =N61/(2025-F61) -> 3072.5704 | N61: =K61-O61 -> 15362.852 | O61: =K61*(1-L61)^(2025-F61) -> 16177.148 | R61: Assistant Administartion Manager | T61: In Use
A62: Office equipments | B62: GOK | D62: NGOB/01/033 | E62: Microwave | F62: 2020 | H62: Nairobi | I62: Nairobi | J62: 2029 | K62: 14110 | L62: 0.125 | M62: =N62/(2025-F62) -> 1374.571 | N62: =K62-O62 -> 6872.8549 | O62: =K62*(1-L62)^(2025-F62) -> 7237.1451 | R62: Assistant Administartion Manager | T62: In Use
A63: Office equipments | B63: GOK | D63: NGOB/01/0187 | E63: Mettallic cabinet 4 drawers | F63: 2016 | H63: Mombasa | I63: Mombasa | K63: 22285 | L63: 0.125 | M63: =N63/(2025-F63) -> 1731.649 | N63: =K63-O63 -> 15584.841 | O63: =K63*(1-L63)^(2025-F63) -> 6700.1591 | R63: Bakari Chara | T63: In Use
A64: Office equipments | B64: GOK | D64: NGOB/01/0188 | E64: Mettallic cabinet 4 drawers | F64: 2021 | H64: Mombasa | I64: Mombasa | K64: 29450 | L64: 0.125 | M64: =N64/(2025-F64) -> 3046.7377 | N64: =K64-O64 -> 12186.951 | O64: =K64*(1-L64)^(2025-F64) -> 17263.049 | R64: Bakari Chara | T64: In Use
A65: Office equipments | B65: GOK | D65: NGOB/01/0189 | E65: Mettallic cabinet two door | F65: 2020 | H65: Mombasa | I65: Mombasa | K65: 25778 | L65: 0.125 | M65: =N65/(2025-F65) -> 2511.2467 | N65: =K65-O65 -> 12556.233 | O65: =K65*(1-L65)^(2025-F65) -> 13221.767 | R65: Bakari Chara | T65: In Use
A66: Office equipments | B66: GOK | D66: NGOB/03/0071 | E66: Water dispensor | F66: 2020 | H66: Mombasa | I66: Mombasa | K66: 25778 | L66: 0.125 | M66: =N66/(2025-F66) -> 2511.2467 | N66: =K66-O66 -> 12556.233 | O66: =K66*(1-L66)^(2025-F66) -> 13221.767 | R66: Bakari Chara | T66: In Use
K67: =SUM(K2:K66) -> 28954397 | M67: =SUM(M2:M66) -> 2733643.1 | N67: =SUM(N2:N66) -> 14800395 | O67: =SUM(O2:O66) -> 14154002
A69: Prepared by: Doris Muthini Designation: Manager SCM Date: 30th June 2025
A70: Checked by: David NjaneDesignation: Finance Manager Date: 30th June 2025
A71: Authorized by: Dr. Laxmana P. Kiptoo Designation: Director/Chief Executive Officer Date: 30th June 2025

Sheet ICT Computer Register 
A1: ICT/Computer register
B2: Asset Description | C2: Financed by/ source of funds | D2: Serial number | E2: Tag number | F2: Make & Model | G2: Date of Delivery / installation | H2: PV number | I2: Original Location | J2: Current Location | K2: Replacement Date (if applicable) | L2: Purchase amount | M2: Depreciation rate | N2: Annual depreciation | O2: Accumulated depreciation | P2: Net Book Value | Q2: Date of disposal | R2: Disposal value | S2: Responsible officer | T2: Asset condition | U2: Notes
B3: CPU Monitor Keyboard | C3: GOK | D3: CZ018C7P 3CQ0030ZLZ | E3: NGOB/02/0230 NGOB/02/0239 NGOB/02/0038 | F3: HP PRODESK INTEL(R) CORE™I5-9500 4GB,500GB 17''inch LED HP Monitor | G3: 2020 | I3: Nairobi | J3: Nairobi | K3: 2023 | L3: 98000 | M3: 0.3 | N3: =O3/(2025-G3) -> 16305.828 | O3: =L3-P3 -> 81529.14 | P3: =L3*(1-M3)^(2025-G3) -> 16470.86 | S3: David Njane | T3: Good | U3: In use
B4: CPU Monitor Keyboard | C4: GOK | D4: CZC018C2FS 3CQ0030ZMB | E4: NGOB/02/0053 NGOB/02/0051 NGOB/02/0052 | F4: HP PRODESK INTEL(R) CORE™I5-9500 4GB,500GB 17''inch LED HP Monitor | G4: 2020 | I4: Nairobi | J4: Nairobi | K4: 2023 | L4: 98000 | M4: 0.3 | N4: =O4/(2025-G4) -> 16305.828 | O4: =L4-P4 -> 81529.14 | P4: =L4*(1-M4)^(2025-G4) -> 16470.86 | S4: Stephen Monyoncho | T4: Good | U4: In use
B5: CPU Monitor Keyboard | C5: GOK | D5: CZ018C2DG 3CQ0030W1V | E5: NGOB/02/0129 NGOB/02/0130 NGOB/02/0131 | F5: HP PRODESK INTEL(R) CORE™I5-9500 4GB,500GB 17''inch LED HP Monitor | G5: 2020 | I5: Nairobi | J5: Nairobi | K5: 2023 | L5: 98000 | M5: 0.3 | N5: =O5/(2025-G5) -> 16305.828 | O5: =L5-P5 -> 81529.14 | P5: =L5*(1-M5)^(2025-G5) -> 16470.86 | S5: Racheal Kimongo | T5: Good | U5: In use
B6: CPU Monitor Keyboard | C6: GOK | D6: CZ018CZ80 3CQ0030W1P | E6: NGOB/02/0053 NGOB/02/0073 NGOB/02/0083 | F6: HP PRODESK INTEL(R) CORE™I5-9500 4GB,500GB 17''inch LED HP Monitor | G6: 2020 | I6: Nairobi | J6: Nairobi | K6: 2023 | L6: 98000 | M6: 0.3 | N6: =O6/(2025-G6) -> 16305.828 | O6: =L6-P6 -> 81529.14 | P6: =L6*(1-M6)^(2025-G6) -> 16470.86 | S6: Steve Kamande | T6: Good | U6: In use
B7: CPU Monitor Keyboard | C7: GOK | D7: C2C018C510 3CQ0030ZKB | E7: NGOB/02/0220 NGOB/02/0219 NGOB/02/0221 | F7: HP PRODESK INTEL(R) CORE™I5-9500 4GB,500GB 17''inch LED HP Monitor | G7: 2020 | I7: Nairobi | J7: Nairobi | K7: 2023 | L7: 98000 | M7: 0.3 | N7: =O7/(2025-G7) -> 16305.828 | O7: =L7-P7 -> 81529.14 | P7: =L7*(1-M7)^(2025-G7) -> 16470.86 | S7: Arasa Mokua | T7: Good | U7: In use
B8: CPU Monitor Keyboard | C8: GOK | D8: C2C01807S 3CQ00312B7 | E8: NGOB/02/0217 NGOB/02/0216 NGOB/02/0218 | F8: HP PRODESK INTEL(R) CORE™I5-9500 4GB,500GB 17''inch LED HP Monitor | G8: 2020 | I8: Nairobi | J8: Nairobi | K8: 2023 | L8: 98000 | M8: 0.3 | N8: =O8/(2025-G8) -> 16305.828 | O8: =L8-P8 -> 81529.14 | P8: =L8*(1-M8)^(2025-G8) -> 16470.86 | S8: Dorris Muthini | T8: Good | U8: In use
B9: CPU Monitor Keyboard | C9: GOK | D9: CZCO18BYGK 3CQ0030Z8H | E9: NGOB/02/0028 NGOB/02/0029 NGOB/02/0030 | F9: HP PRODESK INTEL(R) CORE™I5-9500 4GB,500GB 17''inch LED HP Monitor | G9: 2020 | I9: Nairobi | J9: Nairobi | K9: 2023 | L9: 98000 | M9: 0.3 | N9: =O9/(2025-G9) -> 16305.828 | O9: =L9-P9 -> 81529.14 | P9: =L9*(1-M9)^(2025-G9) -> 16470.86 | S9: Eric Mutua | T9: Good | U9: In use
B10: CPU Monitor Keyboard | C10: GOK | D10: CZCO18BYK4 3CQ0030Z9H | E10: NGOB/02/0091 NGOB/02/0021 NGOB/02/0022 | F10: HP PRODESK INTEL(R) CORE™I5-9500 4GB,500GB 17''inch LED HP Monitor | G10: 2020 | I10: Nairobi | J10: Nairobi | K10: 2023 | L10: 98000 | M10: 0.3 | N10: =O10/(2025-G10) -> 16305.828 | O10: =L10-P10 -> 81529.14 | P10: =L10*(1-M10)^(2025-G10) -> 16470.86 | S10: Amina Matheka | T10: Good | U10: In use
B11: CPU Monitor Keyboard | C11: GOK | D11: CZCO18C2HJ 3CQ0030WC2 | E11: NGOB/02/0020 NGOB/02/0032 NGOB/02/0033 | F11: HP PRODESK INTEL(R) CORE™I5-9500 4GB,500GB 17''inch LED HP Monitor | G11: 2020 | I11: Nairobi | J11: Nairobi | K11: 2023 | L11: 98000 | M11: 0.3 | N11: =O11/(2025-G11) -> 16305.828 | O11: =L11-P11 -> 81529.14 | P11: =L11*(1-M11)^(2025-G11) -> 16470.86 | S11: Josephine Wanjala | T11: Good | U11: In use
B12: CPU Monitor Keyboard | C12: GOK | D12: CZCO18COBT 3CQ0031011 | E12: NGOB/02/0024 NGOB/02/0025 NGOB/02/0026 | F12: HP PRODESK INTEL(R) CORE™I5-9500 4GB,500GB 17''inch LED HP Monitor | G12: 2020 | I12: Nairobi | J12: Nairobi | K12: 2023 | L12: 98000 | M12: 0.3 | N12: =O12/(2025-G12) -> 16305.828 | O12: =L12-P12 -> 81529.14 | P12: =L12*(1-M12)^(2025-G12) -> 16470.86 | S12: Yvonne Ambundo | T12: Good | U12: In use
B13: CPU Monitor Keyboard | C13: GOK | D13: 4CE938205W 3CQ9191LJD | E13: NGOB/02/0159 NGOB/02/0158 NGOB/02/0160 | F13: HP PRODESK INTEL(R) CORE™I5-9500 4GB,500GB 17''inch LED HP Monitor | G13: 2020 | I13: Nairobi | J13: Nairobi | K13: 2023 | L13: 98000 | M13: 0.3 | N13: =O13/(2025-G13) -> 16305.828 | O13: =L13-P13 -> 81529.14 | P13: =L13*(1-M13)^(2025-G13) -> 16470.86 | S13: Juliet Karari | T13: Good | U13: In use
B14: CPU Monitor Keyboard | C14: GOK | D14: CZC018C28H 3CQ0031XQ1 | E14: NGOB/02/0024 NGOB/02/0025 NGOB/02/0026 | F14: HP PRODESK INTEL(R) CORE™I5-9500 4GB,500GB 17''inch LED HP Monitor | G14: 2020 | I14: Nairobi | J14: Nairobi | K14: 2023 | L14: 98000 | M14: 0.3 | N14: =O14/(2025-G14) -> 16305.828 | O14: =L14-P14 -> 81529.14 | P14: =L14*(1-M14)^(2025-G14) -> 16470.86 | S14: Scholar Mutua | T14: Good | U14: In use
... B40: CPU Monitor Keyboard | C40: GOK | D40: 7P6KB22 CN-OU417N-64180-98JOUMU | E40: NGOB/02/0210 NGOB/02/0209 NGOB/02/0211 | F40: HP PRO 3500 SERIES,INTEL CORE I3 3240, 4GB,500GB 17''inch LED HP Monitor | G40: 2008 | I40: Nairobi | J40: Nairobi | K40: 2011 | L40: 98000 | M40: 0.3 | N40: =O40/(2025-G40) -> 5751.2954 | O40: =L40-P40 -> 97772.022 | P40: =L40*(1-M40)^(2025-G40) -> 227.9779 | S40: HR Department | T40: Good | U40: In use
B41: CPU Monitor Keyboard | C41: GOK | E41: NGOB/02/0121 NGOB/02/0199 NGOB/02/0123 | F41: IMAC PRO | G41: 2020 | I41: Nairobi | J41: Nairobi | K41: 2023 | L41: 670000 | M41: 0.3 | N41: =O41/(2025-G41) -> 111478.62 | O41: =L41-P41 -> 557393.1 | P41: =L41*(1-M41)^(2025-G41) -> 112606.9 | S41: Richard Chesos | T41: Good | U41: In use
B42: CPU Monitor Keyboard | C42: GOK | D42: TRF415W2R 6CM4031GV6 | E42: NGOB/02/0043 NGOB/02/0248 | F42: HP PRO 3500 SERIES,INTEL CORE I3 3240, 4GB,500GB 17''inch LED HP Monitor | G42: 2015 | I42: Nairobi | J42: Nairobi | K42: 2018 | L42: 95042 | M42: 0.3 | N42: =O42/(2025-G42) -> 9235.7299 | O42: =L42-P42 -> 92357.299 | P42: =L42*(1-M42)^(2025-G42) -> 2684.7013 | S42: David Njane | T42: Good | U42: In use
B43: CPU Monitor Keyboard | C43: GOK | D43: CZCO18BYG6 3CQ0030Z96 | E43: NGOB/02/0044 NGOB/02/0046 NGOB/02/0048 | F43: INTEL CORE I3 4TH GENERATION,4GB, 500 GB 17''inch LED HP Monitor | G43: 2015 | I43: Nairobi | J43: Nairobi | K43: 2018 | L43: 95042 | M43: 0.3 | N43: =O43/(2025-G43) -> 9235.7299 | O43: =L43-P43 -> 92357.299 | P43: =L43*(1-M43)^(2025-G43) -> 2684.7013 | S43: Muktar Mohamed | T43: Good | U43: In use
B44: CPU Monitor Keyboard | C44: GOK | D44: DB3357 CN-OR735N-64180-9CJ-1HEAU | E44: NGOB/02/0162 NGOB/02/0056 NGOB/02/0163 | F44: INTEL CORE I3 4TH GENERATION,4GB, 500 GB 17''inch LED HP Monitor | G44: 2015 | I44: Nairobi | J44: Nairobi | K44: 2018 | L44: 95042 | M44: 0.3 | N44: =O44/(2025-G44) -> 9235.7299 | O44: =L44-P44 -> 92357.299 | P44: =L44*(1-M44)^(2025-G44) -> 2684.7013 | S44: Brian Oure | T44: Good | U44: In use
B45: CPU Monitor Keyboard | C45: GOK | D45: 5QQX232 CN-ONJVXM-72872-4BB-E00B | E45: NGOB/02/0155 NGOB/02/0154 NGOB/02/0156 | F45: DELL OPTIPLEX 3020 INTEL CORE I3 4GB,500GB 17''inch LED HDell Monitor | G45: 2015 | I45: Nairobi | J45: Nairobi | K45: 2018 | L45: 95042 | M45: 0.3 | N45: =O45/(2025-G45) -> 9235.7299 | O45: =L45-P45 -> 92357.299 | P45: =L45*(1-M45)^(2025-G45) -> 2684.7013 | S45: Mercy Soy | T45: Good | U45: In use
B46: CPU Monitor Keyboard | C46: GOK | D46: B3XY232 CN-ONJVXM-72872-4BB-DY5B | E46: NGOB/02/0055 NGOB/02/0016 NGOB/02/0009 | F46: DELL OPTIPLEX 3020 INTEL CORE I3 4GB,500GB 17''inch LED HP Monitor | G46: 2015 | I46: Nairobi | J46: Nairobi | K46: 2018 | L46: 95042 | M46: 0.3 | N46: =O46/(2025-G46) -> 9235.7299 | O46: =L46-P46 -> 92357.299 | P46: =L46*(1-M46)^(2025-G46) -> 2684.7013 | S46: Zulekha Siyat | T46: Good | U46: In use
B47: CPU Monitor Keyboard | C47: GOK | D47: 54XY23 CN-O65TPN-64880-512-8Y3I | E47: NGOB/02/0239 NGOB/02/0262 NGOB/02/0263 | F47: INTEL CORE I3 4TH GENERATION,4GB, 500 GB , 200 GB 17''inch LED HP Monitor | G47: 2015 | I47: Nairobi | J47: Nairobi | K47: 2018 | L47: 79494 | M47: 0.3 | N47: =O47/(2025-G47) -> 7724.8491 | O47: =L47-P47 -> 77248.491 | P47: =L47*(1-M47)^(2025-G47) -> 2245.5087 | S47: Duncan Mokaya | T47: Good | U47: In use
B48: CPU Monitor Keyboard | C48: GOK | D48: 2P25732 CN-0657PN-64180-512-A8GI | E48: NGOB/02/0173 NGOB/02/0005 NGOB/02/0 | F48: DELL OPTIPLEX 3020 INTEL CORE I3 4GB,500GB 17''inch LED Dell Monitor | G48: 2015 | I48: Nairobi | J48: Nairobi | K48: 2018 | L48: 79494 | M48: 0.3 | N48: =O48/(2025-G48) -> 7724.8491 | O48: =L48-P48 -> 77248.491 | P48: =L48*(1-M48)^(2025-G48) -> 2245.5087 | S48: Ephy Nafuna | T48: Good | U48: In use
B49: CPU Monitor Keyboard | C49: GOK | D49: 4CE93815X3 3CQ919KXR | E49: NGOB/02/0201 NGOB/02/0200 NGOB/02/0202 | F49: HP INTEL CORE I7 7th GENERATION ,4GB,500GB 17''inch LED HP Monitor | G49: 2020 | I49: Nairobi | J49: Nairobi | K49: 2023 | L49: 98000 | M49: 0.3 | N49: =O49/(2025-G49) -> 16305.828 | O49: =L49-P49 -> 81529.14 | P49: =L49*(1-M49)^(2025-G49) -> 16470.86 | S49: Payroll Server | T49: Good | U49: In use
B50: CPU Monitor Keyboard | C50: GOK | D50: 9F7KB22 CN-0R735N-64180-9CJ-04WU | E50: NGOB/02/0204 NGOB/02/0203 NGOB/02/0205 | F50: DELL OPTIPLEX 3020 INTEL CORE I3 4GB,500GB 17''inch LED Dell Monitor | G50: 2014 | I50: Nairobi | J50: Nairobi | K50: 2017 | L50: 55680 | M50: 0.3 | N50: =O50/(2025-G50) -> 4961.7295 | O50: =L50-P50 -> 54579.024 | P50: =L50*(1-M50)^(2025-G50) -> 1100.9755 | S50: Beryl Odete | T50: Good | U50: In use
B51: CPU Monitor Keyboard | C51: GOK | D51: BZ15732 CN-0657PN-64180-512-AAHI | E51: NGOB/02/0175 NGOB/02/0174 NGOB/02/0188 | F51: DELL OPTIPLEX 3020 INTEL CORE I3 4GB,500GB 17''inch LED Dell Monitor | G51: 2014 | I51: Nairobi | J51: Nairobi | K51: 2017 | L51: 55680 | M51: 0.3 | N51: =O51/(2025-G51) -> 4961.7295 | O51: =L51-P51 -> 54579.024 | P51: =L51*(1-M51)^(2025-G51) -> 1100.9755 | S51: Peter Ndale | T51: Good | U51: In use
B52: CPU Monitor Keyboard | C52: GOK | D52: 4CE9382O7F 3CQ851OGY6 | E52: NGOB/02/0135 NGOB/02/0136 NGOB/02/0137 | F52: HP PRO DESK400 G4, CORE I7 , 8GB,1TB MICRO TOWER PC 17''inch LED HP Monitor | G52: 2020 | I52: Nairobi | J52: Garissa | K52: 2023 | L52: 107500 | M52: 0.3 | N52: =O52/(2025-G52) -> 17886.495 | O52: =L52-P52 -> 89432.475 | P52: =L52*(1-M52)^(2025-G52) -> 18067.525 | S52: Garissa Office | T52: Good | U52: In use
B53: CPU Monitor Keyboard | C53: GOK | E53: NGOB/02/0228 NGOB/02/0329 NGOB/02/ | F53: HP PRO 3500 SERIES,INTEL CORE I3 3240, 4GB,500GB 21''inch LED HP Monitor | G53: 2008 | I53: Nairobi | J53: Nairobi | K53: 2011 | L53: 0 | M53: 0.3 | N53: =O53/(2025-G53) -> 0 | O53: =L53-P53 -> 0 | P53: =L53*(1-M53)^(2025-G53) -> 0 | S53: Joyce Naisiala | T53: Good | U53: In use
B54: LAPTOP COMPUTER | C54: GOK | D54: 5CD9135LHR | F54: HP Probook 450 G7, 10th Gen Core i7 Intel core, 16GB RAM DDR4, 1TB | G54: 2019 | I54: Nairobi | J54: Nairobi | K54: 2022 | L54: 125900 | M54: 0.3 | N54: =O54/(2025-G54) -> 18514.665 | O54: =L54-P54 -> 111087.99 | P54: =L54*(1-M54)^(2025-G54) -> 14812.009 | S54: Executive Director | T54: Good | U54: In use
B55: LAPTOP COMPUTER | C55: GOK | D55: 5CD0152R6G | F55: HP Probook 450 G7, 10th Gen Core i7 Intel core, 16GB RAM DDR4, 1TB | G55: 2020 | I55: Nairobi | J55: Nairobi | K55: 2023 | L55: 125900 | M55: 0.3 | N55: =O55/(2025-G55) -> 20947.997 | O55: =L55-P55 -> 104739.99 | P55: =L55*(1-M55)^(2025-G55) -> 21160.013 | S55: Deputy Executive Director | T55: Good | U55: In use
B56: LAPTOP COMPUTER | C56: GOK | D56: 5CD0152QZK | F56: HP Probook 450 G7, 10th Gen Core i7 Intel core, 16GB RAM DDR4, 1TB | G56: 2020 | I56: Nairobi | J56: Nairobi | K56: 2023 | L56: 125900 | M56: 0.3 | N56: =O56/(2025-G56) -> 20947.997 | O56: =L56-P56 -> 104739.99 | P56: =L56*(1-M56)^(2025-G56) -> 21160.013 | S56: David Njane | T56: Good | U56: In use
B57: LAPTOP COMPUTER | C57: GOK | D57: 5CD0152R5Y | E57: NGOB/02/0379 | F57: HP Probook 450 G7, 10th Gen Core i7 Intel core, 16GB RAM DDR4, 1TB | G57: 2020 | I57: Nairobi | J57: Nairobi | K57: 2023 | L57: 125900 | M57: 0.3 | N57: =O57/(2025-G57) -> 20947.997 | O57: =L57-P57 -> 104739.99 | P57: =L57*(1-M57)^(2025-G57) -> 21160.013 | S57: Joyce Naisiala | T57: Good | U57: In use
B58: LAPTOP COMPUTER | C58: GOK | D58: 5CD03590FZC | E58: NGOB/02/0023 | F58: HP Probook 450 G7, 10th Gen Core i7 Intel core, 16GB RAM DDR4, 1TB | G58: 2020 | I58: Nairobi | J58: Nairobi | K58: 2023 | L58: 125900 | M58: 0.3 | N58: =O58/(2025-G58) -> 20947.997 | O58: =L58-P58 -> 104739.99 | P58: =L58*(1-M58)^(2025-G58) -> 21160.013 | S58: Amina Matheka | T58: Good | U58: In use
B59: LAPTOP COMPUTER | C59: GOK | D59: 5CD0359OHM | E59: NGOB/02/0027 | F59: HP Probook 450 G7, 10th Gen Core i7 Intel core, 16GB RAM DDR4, 1TB | G59: 2020 | I59: Nairobi | J59: Nairobi | K59: 2023 | L59: 125900 | M59: 0.3 | N59: =O59/(2025-G59) -> 20947.997 | O59: =L59-P59 -> 104739.99 | P59: =L59*(1-M59)^(2025-G59) -> 21160.013 | S59: Yvonne Isichi | T59: Good | U59: In use
B60: LAPTOP COMPUTER | C60: GOK | D60: 5CD0359OHJC | E60: NGOB/02/0276 | F60: HP Probook 450 G7, 10th Gen Core i7 Intel core, 16GB RAM DDR4, 1TB | G60: 2020 | I60: Nairobi | J60: Nairobi | K60: 2023 | L60: 125900 | M60: 0.3 | N60: =O60/(2025-G60) -> 20947.997 | O60: =L60-P60 -> 104739.99 | P60: =L60*(1-M60)^(2025-G60) -> 21160.013 | S60: Josephine Wanjala | T60: Good | U60: In use
B61: LAPTOP COMPUTER | C61: GOK | D61: 5CD0359OJMC | F61: HP Probook 450 G7, 10th Gen Core i7 Intel core, 16GB RAM DDR4, 1TB | G61: 2020 | I61: Nairobi | J61: Nairobi | K61: 2023 | L61: 125900 | M61: 0.3 | N61: =O61/(2025-G61) -> 20947.997 | O61: =L61-P61 -> 104739.99 | P61: =L61*(1-M61)^(2025-G61) -> 21160.013 | S61: Zilpah Kwamboka | T61: Good | U61: In use
B62: LAPTOP COMPUTER | C62: GOK | D62: 5CD0359OH4C | F62: HP Probook 450 G7, 10th Gen Core i7 Intel core, 16GB RAM DDR4, 1TB | G62: 2020 | I62: Nairobi | J62: Nairobi | K62: 2023 | L62: 125900 | M62: 0.3 | N62: =O62/(2025-G62) -> 20947.997 | O62: =L62-P62 -> 104739.99 | P62: =L62*(1-M62)^(2025-G62) -> 21160.013 | S62: Caroline Nyambura | T62: Good | U62: In use
B63: LAPTOP COMPUTER | C63: GOK | D63: 5CD0359OJ4 | F63: HP Probook 450 G7, 10th Gen Core i7 Intel core, 16GB RAM DDR4, 1TB | G63: 2020 | I63: Nairobi | J63: Nairobi | K63: 2023 | L63: 125900 | M63: 0.3 | N63: =O63/(2025-G63) -> 20947.997 | O63: =L63-P63 -> 104739.99 | P63: =L63*(1-M63)^(2025-G63) -> 21160.013 | S63: Isaiah Sang | T63: Good | U63: In use
B64: LAPTOP COMPUTER | C64: GOK | D64: 5CD0359OGWC | F64: HP Probook 450 G7, 10th Gen Core i7 Intel core, 16GB RAM DDR4, 1TB | G64: 2020 | I64: Nairobi | J64: Nairobi | K64: 2023 | L64: 125900 | M64: 0.3 | N64: =O64/(2025-G64) -> 20947.997 | O64: =L64-P64 -> 104739.99 | P64: =L64*(1-M64)^(2025-G64) -> 21160.013 | S64: Beryl Odete | T64: Good | U64: In use
B65: LAPTOP COMPUTER | C65: GOK | D65: 5CD0359OHCC | F65: HP Probook 450 G7, 10th Gen Core i7 Intel core, 16GB RAM DDR4, 1TB | G65: 2020 | I65: Nairobi | J65: Nairobi | K65: 2023 | L65: 125900 | M65: 0.3 | N65: =O65/(2025-G65) -> 20947.997 | O65: =L65-P65 -> 104739.99 | P65: =L65*(1-M65)^(2025-G65) -> 21160.013 | S65: Bernard Bwoma | T65: Good | U65: In use
B66: LAPTOP COMPUTER | C66: GOK | D66: 5CD032LOCZC | F66: HP Probook 450 G7, 10th Gen Core i7 Intel core, 16GB RAM DDR4, 1TB | G66: 2020 | I66: Nairobi | J66: Nairobi | K66: 2023 | L66: 125900 | M66: 0.3 | N66: =O66/(2025-G66) -> 20947.997 | O66: =L66-P66 -> 104739.99 | P66: =L66*(1-M66)^(2025-G66) -> 21160.013 | S66: Lindon Nicolas | T66: Good | U66: In use
B67: LAPTOP COMPUTER | C67: GOK | D67: 5CD032LOCNC | F67: HP Probook 450 G7, 10th Gen Core i7 Intel core, 16GB RAM DDR4, 1TB | G67: 2020 | I67: Nairobi | J67: Nairobi | K67: 2023 | L67: 125900 | M67: 0.3 | N67: =O67/(2025-G67) -> 20947.997 | O67: =L67-P67 -> 104739.99 | P67: =L67*(1-M67)^(2025-G67) -> 21160.013 | S67: Dorris Muthini | T67: Good | U67: In use
B68: LAPTOP COMPUTER | C68: GOK | D68: 5CD0359OKIC | F68: HP Probook 450 G7, 10th Gen Core i7 Intel core, 16GB RAM DDR4, 1TB | G68: 2020 | I68: Nairobi | J68: Nairobi | K68: 2023 | L68: 125900 | M68: 0.3 | N68: =O68/(2025-G68) -> 20947.997 | O68: =L68-P68 -> 104739.99 | P68: =L68*(1-M68)^(2025-G68) -> 21160.013 | S68: Joy Kawira | T68: Good | U68: In use
B69: LAPTOP COMPUTER | C69: GOK | D69: 5CD0359OHQC | F69: HP Probook 450 G7, 10th Gen Core i7 Intel core, 16GB RAM DDR4, 1TB | G69: 2020 | I69: Nairobi | J69: Nairobi | K69: 2023 | L69: 125900 | M69: 0.3 | N69: =O69/(2025-G69) -> 20947.997 | O69: =L69-P69 -> 104739.99 | P69: =L69*(1-M69)^(2025-G69) -> 21160.013 | S69: Richard Chesos | T69: Good | U69: In use
B70: LAPTOP COMPUTER | C70: GOK | D70: 5CD0359OGPC | E70: NGOB/02/0300 | F70: HP Probook 450 G7, 10th Gen Core i7 Intel core, 16GB RAM DDR4, 1TB | G70: 2020 | I70: Nairobi | J70: Nairobi | K70: 2023 | L70: 125900 | M70: 0.3 | N70: =O70/(2025-G70) -> 20947.997 | O70: =L70-P70 -> 104739.99 | P70: =L70*(1-M70)^(2025-G70) -> 21160.013 | S70: Yvonne Gitau | T70: Good | U70: In use
B71: LAPTOP COMPUTER | C71: GOK | D71: 5CD0359OHB | F71: HP Probook 450 G7, 10th Gen Core i7 Intel core, 16GB RAM DDR4, 1TB | G71: 2020 | I71: Nairobi | J71: Nairobi | K71: 2023 | L71: 125900 | M71: 0.3 | N71: =O71/(2025-G71) -> 20947.997 | O71: =L71-P71 -> 104739.99 | P71: =L71*(1-M71)^(2025-G71) -> 21160.013 | S71: Juliet Karari | T71: Good | U71: In use
B72: LAPTOP COMPUTER | C72: GOK | D72: 5CD0359OJW | F72: HP Probook 450 G7, 10th Gen Core i7 Intel core, 16GB RAM DDR4, 1TB | G72: 2020 | I72: Nairobi | J72: Garissa | K72: 2023 | L72: 125900 | M72: 0.3 | N72: =O72/(2025-G72) -> 20947.997 | O72: =L72-P72 -> 104739.99 | P72: =L72*(1-M72)^(2025-G72) -> 21160.013 | S72: Joseph Kaluu | T72: Good | U72: In use
B73: LAPTOP COMPUTER | C73: GOK | D73: 5CD0359OH9 | E73: NGOB/02/0277 | F73: HP Probook 450 G7, 10th Gen Core i7 Intel core, 16GB RAM DDR4, 1TB | G73: 2020 | I73: Nairobi | J73: Nairobi | K73: 2023 | L73: 125900 | M73: 0.3 | N73: =O73/(2025-G73) -> 20947.997 | O73: =L73-P73 -> 104739.99 | P73: =L73*(1-M73)^(2025-G73) -> 21160.013 | S73: Maureen Kimunguyi | T73: Good | U73: In use
B74: LAPTOP COMPUTER | C74: GOK | D74: 5CD0359OHLC | E74: NGOB/02/0049 | F74: HP Probook 450 G7, 10th Gen Core i7 Intel core, 16GB RAM DDR4, 1TB | G74: 2020 | I74: Nairobi | J74: Nairobi | K74: 2023 | L74: 125900 | M74: 0.3 | N74: =O74/(2025-G74) -> 20947.997 | O74: =L74-P74 -> 104739.99 | P74: =L74*(1-M74)^(2025-G74) -> 21160.013 | S74: Muktar Mohamed | T74: Good | U74: In use
B75: LAPTOP COMPUTER | C75: GOK | D75: 5CD032LODV | F75: HP Probook 450 G7, 10th Gen Core i7 Intel core, 16GB RAM DDR4, 1TB | G75: 2020 | I75: Nairobi | J75: Nairobi | K75: 2023 | L75: 125900 | M75: 0.3 | N75: =O75/(2025-G75) -> 20947.997 | O75: =L75-P75 -> 104739.99 | P75: =L75*(1-M75)^(2025-G75) -> 21160.013 | S75: Mokua Arasa | T75: Good | U75: In use
B76: LAPTOP COMPUTER | C76: GOK | D76: 5CD0359OHO | F76: HP Probook 450 G7, 10th Gen Core i7 Intel core, 16GB RAM DDR4, 1TB | G76: 2020 | I76: Nairobi | J76: Nairobi | K76: 2023 | L76: 125900 | M76: 0.3 | N76: =O76/(2025-G76) -> 20947.997 | O76: =L76-P76 -> 104739.99 | P76: =L76*(1-M76)^(2025-G76) -> 21160.013 | S76: Margaret Nyawira | T76: Good | U76: In use
B77: LAPTOP COMPUTER | C77: GOK | D77: 5CD032LOF3C | E77: NGOB/02/0310 | F77: HP Probook 450 G7, 10th Gen Core i7 Intel core, 16GB RAM DDR4, 1TB | G77: 2020 | I77: Nairobi | J77: Nairobi | K77: 2023 | L77: 125900 | M77: 0.3 | N77: =O77/(2025-G77) -> 20947.997 | O77: =L77-P77 -> 104739.99 | P77: =L77*(1-M77)^(2025-G77) -> 21160.013 | S77: Josephine Ngatia | T77: Good | U77: In use
B78: LAPTOP COMPUTER | C78: GOK | D78: 5CD03590HQ | F78: HP Probook 450 G7, 10th Gen Core i7 Intel core, 16GB RAM DDR4, 1TB | G78: 2020 | I78: Nairobi | J78: Nairobi | K78: 2023 | L78: 125900 | M78: 0.3 | N78: =O78/(2025-G78) -> 20947.997 | O78: =L78-P78 -> 104739.99 | P78: =L78*(1-M78)^(2025-G78) -> 21160.013 | S78: Stephen Monyoncho | T78: Good | U78: In use
B79: LAPTOP COMPUTER | C79: GOK | D79: 5CD032LOFD | F79: HP Probook 450 G7, 10th Gen Core i7 Intel core, 16GB RAM DDR4, 1TB | G79: 2020 | I79: Nairobi | J79: Nairobi | K79: 2023 | L79: 125900 | M79: 0.3 | N79: =O79/(2025-G79) -> 20947.997 | O79: =L79-P79 -> 104739.99 | P79: =L79*(1-M79)^(2025-G79) -> 21160.013 | S79: Mercy Soy | T79: Good | U79: In use
B80: LAPTOP COMPUTER | C80: GOK | D80: 5CD032LOFDC | E80: NGOB/02/0176 | F80: HP Probook 450 G7, 10th Gen Core i7 Intel core, 16GB RAM DDR4, 1TB | G80: 2020 | I80: Nairobi | J80: Nakuru | K80: 2023 | L80: 125900 | M80: 0.3 | N80: =O80/(2025-G80) -> 20947.997 | O80: =L80-P80 -> 104739.99 | P80: =L80*(1-M80)^(2025-G80) -> 21160.013 | S80: James Onkoba | T80: Good | U80: In use
B81: LAPTOP COMPUTER | C81: GOK | D81: 5CD03590HFC | F81: HP Probook 450 G7, 10th Gen Core i7 Intel core, 16GB RAM DDR4, 1TB | G81: 2020 | I81: Nairobi | J81: Nairobi | K81: 2023 | L81: 125900 | M81: 0.3 | N81: =O81/(2025-G81) -> 20947.997 | O81: =L81-P81 -> 104739.99 | P81: =L81*(1-M81)^(2025-G81) -> 21160.013 | S81: Betty Odero | T81: Good | U81: In use
B82: LAPTOP COMPUTER | C82: GOK | D82: 5CD032LO9G | E82: NGOB/02/0278 | F82: HP Probook 450 G7, 10th Gen Core i7 Intel core, 16GB RAM DDR4, 1TB | G82: 2020 | I82: Nairobi | J82: Nairobi | K82: 2023 | L82: 125900 | M82: 0.3 | N82: =O82/(2025-G82) -> 20947.997 | O82: =L82-P82 -> 104739.99 | P82: =L82*(1-M82)^(2025-G82) -> 21160.013 | S82: Yvonne Wangui | T82: Good | U82: In use
B83: LAPTOP COMPUTER | C83: GOK | D83: 5CD03590JL | F83: HP Probook 450 G7, 10th Gen Core i7 Intel core, 16GB RAM DDR4, 1TB | G83: 2020 | I83: Nairobi | J83: Nairobi | K83: 2023 | L83: 125900 | M83: 0.3 | N83: =O83/(2025-G83) -> 20947.997 | O83: =L83-P83 -> 104739.99 | P83: =L83*(1-M83)^(2025-G83) -> 21160.013 | S83: Beatrice Topisia | T83: Good | U83: In use
B84: LAPTOP COMPUTER | C84: GOK | D84: 5CD032L0F0 | E84: NGOB/02/0191 | F84: HP Probook 450 G7, 10th Gen Core i7 Intel core, 16GB RAM DDR4, 1TB | G84: 2020 | I84: Nairobi | J84: Eldoret | K84: 2023 | L84: 125900 | M84: 0.3 | N84: =O84/(2025-G84) -> 20947.997 | O84: =L84-P84 -> 104739.99 | P84: =L84*(1-M84)^(2025-G84) -> 21160.013 | S84: Caroline Kimaiyo | T84: Good | U84: In use
B85: LAPTOP COMPUTER | C85: GOK | D85: 5CD03590JB | F85: HP Probook 450 G7, 10th Gen Core i7 Intel core, 16GB RAM DDR4, 1TB | G85: 2020 | I85: Nairobi | J85: Nairobi | K85: 2023 | L85: 125900 | M85: 0.3 | N85: =O85/(2025-G85) -> 20947.997 | O85: =L85-P85 -> 104739.99 | P85: =L85*(1-M85)^(2025-G85) -> 21160.013 | S85: Bernandette Nzomo | T85: Good | U85: In use
B86: LAPTOP COMPUTER | C86: GOK | D86: CND446COD1 | F86: HP PRO BOOK, CORE I7,8GB,1TB | G86: 2015 | I86: Nairobi | J86: Nairobi | K86: 2018 | L86: 1 | M86: 0.3 | N86: =O86/(2025-G86) -> 0.097175248 | O86: =L86-P86 -> 0.97175248 | P86: =L86*(1-M86)^(2025-G86) -> 0.028247525 | S86: Francis Tumuti | T86: Good | U86: In use
B87: PRINTER/COPIER | C87: GOK | D87: VIC4815045 | E87: NGOB/02/0212 | F87: Kyocera FS 625MFP | G87: 2015 | I87: Nairobi | J87: Nairobi | K87: 2018 | L87: 223521 | M87: 0.3 | N87: =O87/(2025-G87) -> 21720.708 | O87: =L87-P87 -> 217207.08 | P87: =L87*(1-M87)^(2025-G87) -> 6313.915 | S87: ICT | T87: Good | U87: In use
B88: PRINTER/COPIER | C88: GOK | D88: CNCJN25532 | F88: HP Laserjet P2055 | G88: 2011 | I88: Nairobi | J88: Nairobi | K88: 2014 | L88: 23500 | M88: 0.3 | N88: =O88/(2025-G88) -> 1667.187 | O88: =L88-P88 -> 23340.618 | P88: =L88*(1-M88)^(2025-G88) -> 159.38242 | S88: Beatrice Topisia | T88: Good | U88: In use
B89: PRINTER/COPIER | C89: GOK | D89: CNCHB36051 | E89: NGOB/02/0117 | F89: HP Laserjet CP1025 Color | G89: 2011 | I89: Nairobi | J89: Nairobi | K89: 2012 | L89: 40000 | M89: 0.3 | N89: =O89/(2025-G89) -> 2837.7651 | O89: =L89-P89 -> 39728.711 | P89: =L89*(1-M89)^(2025-G89) -> 271.28923 | S89: Bernard Bwoma | T89: Good | U89: In use
B90: PRINTER/COPIER | C90: GOK | D90: CNCJN25537 | E90: NGOB/02/0054 | F90: HP Laserjet P2055 | G90: 2011 | I90: Nairobi | J90: Nairobi | K90: 2014 | L90: 23500 | M90: 0.3 | N90: =O90/(2025-G90) -> 1667.187 | O90: =L90-P90 -> 23340.618 | P90: =L90*(1-M90)^(2025-G90) -> 159.38242 | S90: Allan Kashoka | T90: Good | U90: In use
B91: PRINTER/COPIER | C91: GOK | D91: CNC1740058 | E91: NGOB/02/0157 | F91: HP Laserjet P2055 | G91: 2010 | I91: Nairobi | J91: Nairobi | K91: 2013 | L91: 27984 | M91: 0.3 | N91: =O91/(2025-G91) -> 1856.7429 | O91: =L91-P91 -> 27851.144 | P91: =L91*(1-M91)^(2025-G91) -> 132.85576 | S91: Lindon Nicolas | T91: Good | U91: In use
B92: PRINTER/COPIER | C92: GOK | D92: CNBW6CQOL7 | E92: NGOB/02/0068 | F92: HP Laserjet P2015 | G92: 2010 | I92: Nairobi | J92: Nairobi | K92: 2013 | L92: 27984 | M92: 0.3 | N92: =O92/(2025-G92) -> 1856.7429 | O92: =L92-P92 -> 27851.144 | P92: =L92*(1-M92)^(2025-G92) -> 132.85576 | S92: Esther Letting | T92: Good | U92: In use
B93: PRINTER/COPIER | C93: GOK | D93: CNCJB64943 | F93: HP Laserjet P2055d | G93: 2010 | I93: Nairobi | J93: Nairobi | K93: 2013 | L93: 27984 | M93: 0.3 | N93: =O93/(2025-G93) -> 1856.7429 | O93: =L93-P93 -> 27851.144 | P93: =L93*(1-M93)^(2025-G93) -> 132.85576 | S93: Deputy Executive Director | T93: Good | U93: In use
B94: PRINTER/COPIER | C94: GOK | D94: PHC6N28161 | E94: NGOB/02/0003 | F94: HP Laserjet Pro 402dne | G94: 2019 | I94: Nairobi | J94: Nairobi | K94: 2022 | L94: 22544 | M94: 0.3 | N94: =O94/(2025-G94) -> 3315.2868 | O94: =L94-P94 -> 19891.721 | P94: =L94*(1-M94)^(2025-G94) -> 2652.2791 | S94: Margaret Nyawira | T94: Good | U94: In use
B95: PRINTER/COPIER | C95: GOK | D95: 160040-17 | E95: NGOB/02/0054 | F95: KYOCERA Ecosys P2040dn | G95: 2012 | I95: NAKURU | J95: NAKURU | K95: 2012 | L95: 180000 | M95: 0.3 | N95: =O95/(2025-G95) -> 13712 | O95: =L95-P95 -> 178256 | P95: =L95*(1-M95)^(2025-G95) -> 1744.0022 | S95: Nakuru Office | T95: Good | U95: In use
B96: PRINTER/COPIER | C96: GOK | D96: VNH3B04568 | E96: NGOB/02/0001 | F96: Color HP Laserjet Pro M452dn | G96: 2020 | I96: Nairobi | J96: Nairobi | K96: 2023 | L96: 49500 | M96: 0.3 | N96: =O96/(2025-G96) -> 8236.107 | O96: =L96-P96 -> 41180.535 | P96: =L96*(1-M96)^(2025-G96) -> 8319.465 | S96: Executive Director | T96: Good | U96: In use
B97: PRINTER/COPIER | C97: GOK | D97: C359PB00408 | E97: NGOB/02/0264 | F97: Ricoh MP 3055 | G97: 2020 | I97: Nairobi | J97: Nairobi | K97: 2023 | L97: 281350 | M97: 0.3 | N97: =O97/(2025-G97) -> 46812.701 | O97: =L97-P97 -> 234063.51 | P97: =L97*(1-M97)^(2025-G97) -> 47286.494 | S97: ICT | T97: Good | U97: In use
B98: PRINTER/COPIER | C98: GOK | D98: 1419062733 | E98: NGOB/02/0274 | F98: Kyocera Taskalfa 6003i | G98: 2020 | I98: Nairobi | J98: Nairobi | K98: 2023 | L98: 435000 | M98: 0.3 | N98: =O98/(2025-G98) -> 72377.91 | O98: =L98-P98 -> 361889.55 | P98: =L98*(1-M98)^(2025-G98) -> 73110.45 | S98: ICT | T98: Good | U98: In use
B99: PRINTER/COPIER | C99: GOK | D99: QPF2455670 | F99: Kyocera 1203 MX5KLO | G99: 2011 | I99: Nairobi | J99: Nakuru | K99: 2014 | L99: 1 | M99: 0.3 | N99: =O99/(2025-G99) -> 0.070944126 | O99: =L99-P99 -> 0.99321777 | P99: =L99*(1-M99)^(2025-G99) -> 0.0067822307 | S99: Kisumu Office | T99: Good | U99: In use
B100: PRINTER/COPIER | C100: GOK | D100: C359PC00502 | E100: NGOB/02/0501 | F100: Ricoh MP 3055 | G100: 2020 | I100: Nairobi | J100: Kisumu | K100: 2023 | L100: 281350 | M100: 0.3 | N100: =O100/(2025-G100) -> 46812.701 | O100: =L100-P100 -> 234063.51 | P100: =L100*(1-M100)^(2025-G100) -> 47286.494 | S100: Nakuru Office | T100: Good | U100: In use
B101: PRINTER/COPIER | C101: GOK | D101: CNCJB64943 | E101: NGOB/02/0072 | F101: HP Laserjet P2055d | G101: 2010 | I101: Nairobi | J101: Mombasa | K101: 2013 | L101: 27984 | M101: 0.3 | N101: =O101/(2025-G101) -> 1856.7429 | O101: =L101-P101 -> 27851.144 | P101: =L101*(1-M101)^(2025-G101) -> 132.85576 | S101: Bakari Chala | T101: Good | U101: In use
B102: PRINTER/COPIER | C102: GOK | D102: C359PC00562 | E102: NGOB/02/0153 | F102: Ricoh MP 3055 | G102: 2020 | I102: Nairobi | J102: Mombasa | K102: 2013 | L102: 281350 | M102: 0.3 | N102: =O102/(2025-G102) -> 46812.701 | O102: =L102-P102 -> 234063.51 | P102: =L102*(1-M102)^(2025-G102) -> 47286.494 | S102: Mombasa Office | T102: Good | U102: In use
B103: PRINTER/COPIER | C103: GOK | D103: C359PC00567 | E103: NGOB/02/0192 | F103: Ricoh MP 3055 | G103: 2020 | I103: Nairobi | J103: Eldoret | K103: 2013 | L103: 281350 | M103: 0.3 | N103: =O103/(2025-G103) -> 46812.701 | O103: =L103-P103 -> 234063.51 | P103: =L103*(1-M103)^(2025-G103) -> 47286.494 | S103: Eldoret Office | T103: Good | U103: In use
B104: PRINTER/COPIER | C104: GOK | D104: C359PC00550 | E104: NGOB/02/0142 | F104: Ricoh MP 3055 | G104: 2020 | I104: Nairobi | J104: Garissa | K104: 2013 | L104: 281350 | M104: 0.3 | N104: =O104/(2025-G104) -> 46812.701 | O104: =L104-P104 -> 234063.51 | P104: =L104*(1-M104)^(2025-G104) -> 47286.494 | S104: Garissa Office | T104: Good | U104: In use
B105: UPS | C105: GOK | D105: 1Q1129007755 | E105: NGOB/02/0306 | F105: APC RT 5000 | G105: 2014 | I105: Nairobi | J105: Nairobi | K105: 2017 | L105: 250000 | M105: 0.3 | N105: =O105/(2025-G105) -> 22277.88 | O105: =L105-P105 -> 245056.68 | P105: =L105*(1-M105)^(2025-G105) -> 4943.3169 | S105: ICT | T105: Good | U105: In use
B106: UPS | C106: GOK | D106: N50631027202 | E106: NGOB/02/0307 | F106: APC RT 3000 | G106: 2008 | I106: Nairobi | J106: Nairobi | K106: 2011 | L106: 265000 | M106: 0.3 | N106: =O106/(2025-G106) -> 15551.972 | O106: =L106-P106 -> 264383.53 | P106: =L106*(1-M106)^(2025-G106) -> 616.47086 | S106: ICT | T106: Good | U106: In use
B107: UPS | C107: GOK | D107: 3B1402X22286 | F107: APC RT 650 | G107: 2008 | I107: Nairobi | J107: Nairobi | K107: 2011 | L107: 265000 | M107: 0.3 | N107: =O107/(2025-G107) -> 15551.972 | O107: =L107-P107 -> 264383.53 | P107: =L107*(1-M107)^(2025-G107) -> 616.47086 | S107: Executive Director | T107: Good | U107: In use
B108: UPS | C108: GOK | D108: AS2107151772 | E108: NGOB/02/0302 | F108: APC C1500 | G108: 2021 | I108: Nairobi | J108: Nairobi | K108: 2024 | L108: 265000 | M108: 0.3 | N108: =O108/(2025-G108) -> 50343.375 | O108: =L108-P108 -> 201373.5 | P108: =L108*(1-M108)^(2025-G108) -> 63626.5 | S108: ICT | T108: Good | U108: In use
B109: UPS | C109: GOK | D109: AS2105143500 | E109: NGOB/02/0303 | F109: APC C3000 | G109: 2021 | I109: Nairobi | J109: Nairobi | K109: 2024 | L109: 265000 | M109: 0.3 | N109: =O109/(2025-G109) -> 50343.375 | O109: =L109-P109 -> 201373.5 | P109: =L109*(1-M109)^(2025-G109) -> 63626.5 | S109: ICT | T109: Good | U109: In use
B110: PROJECTOR | C110: GOK | D110: V9HK5301484 | E110: NGOB/02/0378 | F110: Epson H551B | G110: 2015 | I110: Nairobi | J110: Nairobi | K110: 2018 | L110: 150000 | M110: 0.3 | N110: =O110/(2025-G110) -> 14576.287 | O110: =L110-P110 -> 145762.87 | P110: =L110*(1-M110)^(2025-G110) -> 4237.1287 | S110: ICT | T110: Good | U110: In use
B111: FIREWALL | C111: GOK | D111: FG4HOE5819902946 | E111: NGOB/02/0309 | F111: Fortinet/ Fortigate 400E | G111: 2021 | I111: Nairobi | J111: Nairobi | K111: 2024 | L111: 1 | M111: 0.3 | N111: =O111/(2025-G111) -> 0.189975 | O111: =L111-P111 -> 0.7599 | P111: =L111*(1-M111)^(2025-G111) -> 0.2401 | S111: ICT | T111: Good | U111: In use
B112: ROUTER | C112: GOK | D112: FCZ1414C35V | F112: Cisco 2800 | G112: 2010 | I112: Nairobi | J112: Nairobi | K112: 2013 | L112: 147168 | M112: 0.3 | N112: =O112/(2025-G112) -> 9764.6207 | O112: =L112-P112 -> 146469.31 | P112: =L112*(1-M112)^(2025-G112) -> 698.68913 | S112: ICT | T112: Good | U112: In use
B113: ROUTER | C113: GOK | D113: 0 | F113: Cisco 2800 | G113: 2010 | I113: Nairobi | J113: Kisumu | K113: 2013 | L113: 147168 | M113: 0.3 | N113: =O113/(2025-G113) -> 9764.6207 | O113: =L113-P113 -> 146469.31 | P113: =L113*(1-M113)^(2025-G113) -> 698.68913 | S113: ICT | T113: Good | U113: In use
B114: ROUTER | C114: GOK | D114: 0 | F114: Cisco 2800 | G114: 2021 | I114: Nairobi | J114: Mombasa | K114: 2013 | L114: 147168 | M114: 0.3 | N114: =O114/(2025-G114) -> 27958.241 | O114: =L114-P114 -> 111832.96 | P114: =L114*(1-M114)^(2025-G114) -> 35335.037 | S114: ICT | T114: Good | U114: In use
B115: SWITCH | C115: GOK | D115: F3063AA5009329 | F115: DLINK DES-1016D, 24 PORT | G115: 2021 | I115: Nairobi | J115: Nairobi | K115: 0 | L115: 1 | M115: 0.3 | N115: =O115/(2025-G115) -> 0.189975 | O115: =L115-P115 -> 0.7599 | P115: =L115*(1-M115)^(2025-G115) -> 0.2401 | S115: ICT | T115: Good | U115: In use
B116: SWITCH | C116: GOK | D116: DRC2AA6002102 | F116: DLINK DGS-1024D, 24 PORT | G116: 2021 | I116: Nairobi | J116: Nairobi | K116: 0 | L116: 1 | M116: 0.3 | N116: =O116/(2025-G116) -> 0.189975 | O116: =L116-P116 -> 0.7599 | P116: =L116*(1-M116)^(2025-G116) -> 0.2401 | S116: ICT | T116: Good | U116: In use
B117: SWITCH | C117: GOK | D117: F30H162000283 | F117: DLINK DES-1024D, 24 PORT | G117: 2021 | I117: Nairobi | J117: Nairobi | K117: 0 | L117: 1 | M117: 0.3 | N117: =O117/(2025-G117) -> 0.189975 | O117: =L117-P117 -> 0.7599 | P117: =L117*(1-M117)^(2025-G117) -> 0.2401 | S117: ICT | T117: Good | U117: In use
B118: SWITCH | C118: GOK | D118: FCW1809AOKN | F118: CISCO 2960 X SERIES, 24 PORT | G118: 2021 | I118: Nairobi | J118: Nairobi | K118: 0 | L118: 400000 | M118: 0.3 | N118: =O118/(2025-G118) -> 75990 | O118: =L118-P118 -> 303960 | P118: =L118*(1-M118)^(2025-G118) -> 96040 | S118: ICT | T118: Good | U118: In use
B119: SWITCH | C119: GOK | D119: 0 | F119: DLINK , 16 PORT | G119: 2021 | I119: Nairobi | J119: Kisumu | K119: 0 | L119: 1 | M119: 0.3 | N119: =O119/(2025-G119) -> 0.189975 | O119: =L119-P119 -> 0.7599 | P119: =L119*(1-M119)^(2025-G119) -> 0.2401 | S119: ICT | T119: Good | U119: In use
B120: SWITCH | C120: GOK | D120: 0 | F120: TP LINK , 16 PORT | G120: 2021 | I120: Nairobi | J120: Mombasa | K120: 0 | L120: 1 | M120: 0.3 | N120: =O120/(2025-G120) -> 0.189975 | O120: =L120-P120 -> 0.7599 | P120: =L120*(1-M120)^(2025-G120) -> 0.2401 | S120: ICT | T120: Good | U120: In use
B121: SWITCH | C121: GOK | D121: 0 | F121: DLINK DES-1024D, 24 PORT | G121: 2021 | I121: Nairobi | J121: Nairobi | K121: 0 | L121: 1 | M121: 0.3 | N121: =O121/(2025-G121) -> 0.189975 | O121: =L121-P121 -> 0.7599 | P121: =L121*(1-M121)^(2025-G121) -> 0.2401 | S121: ICT | T121: Good | U121: In use
B122: SWITCH | C122: GOK | D122: 210235A3MT9217Q0005G | E122: NGOB/02/0382 | F122: H3C S5560 Series 46 Port | G122: 2021 | I122: Nairobi | J122: Nairobi | K122: 2024 | L122: 1 | M122: 0.3 | N122: =O122/(2025-G122) -> 0.189975 | O122: =L122-P122 -> 0.7599 | P122: =L122*(1-M122)^(2025-G122) -> 0.2401 | S122: ICT | T122: Good | U122: In use
B123: SWITCH | C123: GOK | D123: 210235A3MT9217Q0005F | E123: NGOB/02/0383 | F123: H3C S5560 Series 46 Port | G123: 2021 | I123: Nairobi | J123: Nairobi | K123: 2024 | L123: 1 | M123: 0.3 | N123: =O123/(2025-G123) -> 0.189975 | O123: =L123-P123 -> 0.7599 | P123: =L123*(1-M123)^(2025-G123) -> 0.2401 | S123: ICT | T123: Good | U123: In use
B124: SWITCH | C124: GOK | D124: 210235A2D6H2170C0002 | E124: NGOB/02/0384 | F124: H3C S6860 Series | G124: 2021 | I124: Nairobi | J124: Nairobi | K124: 2024 | L124: 1 | M124: 0.3 | N124: =O124/(2025-G124) -> 0.189975 | O124: =L124-P124 -> 0.7599 | P124: =L124*(1-M124)^(2025-G124) -> 0.2401 | S124: ICT | T124: Good | U124: In use
B125: WIFI DEVICE | C125: GOK | D125: 1337G 24A43C0274F4 | F125: UNIFI | G125: 2015 | I125: Nairobi | J125: Nairobi | K125: 2018 | L125: 42000 | M125: 0.3 | N125: =O125/(2025-G125) -> 4081.3604 | O125: =L125-P125 -> 40813.604 | P125: =L125*(1-M125)^(2025-G125) -> 1186.396 | S125: ICT | T125: Good | U125: In use
...

Sheet Furniture&Fittings 
A1: Asset Description | B1: Financed by/ source of funds | C1: Serial number | D1: Tag number | E1: Make & Model | F1: Date of Delivery / installation | G1: PV number | H1: Original Location | I1: Current Location | J1: Replacement Date (if applicable) | K1: Purchase amount | L1: Depreciation rate | M1: Annual depreciation | N1: Accumulated depreciation | O1: Net Book Value | P1: Date of disposal | Q1: Disposal value | R1: Responsible officer | S1: Asset condition
A2: Office Desk | B2: GOK | C2: N/A | D2: NGOB/01/0342 | E2: L-Shaped W/S 1.8 m | F2: 2005 | H2: Nairobi | I2: Nairobi | J2: 2014 | K2: 16300 | L2: 0.125 | M2: =O2/(2025-F2) -> 56.405138 | N2: =K2-O2 -> 15171.897 | O2: =K2*(1-L2)^(2025-F2) -> 1128.1028 | R2: Joyce Naisiala | S2: Good
A3: Office Desk | B3: GOK | C3: N/A | D3: NGOB/01/0286 | E3: L-Shaped W/S 1.8 m | F3: 2005 | H3: Nairobi | I3: Nairobi | J3: 2014 | K3: 16300 | L3: 0.125 | M3: =O3/(2025-F3) -> 56.405138 | N3: =K3-O3 -> 15171.897 | O3: =K3*(1-L3)^(2025-F3) -> 1128.1028 | R3: Elizabeth Kamau | S3: Good
A4: Office Desk | B4: GOK | C4: N/A | D4: NGOB/01/0127 | E4: L-Shaped W/S 1.8 m | F4: 2005 | H4: Nairobi | I4: Nairobi | J4: 2014 | K4: 16300 | L4: 0.125 | M4: =O4/(2025-F4) -> 56.405138 | N4: =K4-O4 -> 15171.897 | O4: =K4*(1-L4)^(2025-F4) -> 1128.1028 | R4: Administration department | S4: Good
A5: Office Desk | B5: GOK | C5: N/A | D5: NGOB/01/0120 | E5: L-Shaped W/S 1.8 m | F5: 2005 | H5: Nairobi | I5: Nairobi | J5: 2014 | K5: 16300 | L5: 0.125 | M5: =O5/(2025-F5) -> 56.405138 | N5: =K5-O5 -> 15171.897 | O5: =K5*(1-L5)^(2025-F5) -> 1128.1028 | R5: Nick Sankale | S5: Good
A6: Office Desk | B6: GOK | C6: N/A | D6: NGOB/01/0019 | E6: L-Shaped W/S 1.8 m | F6: 2005 | H6: Nairobi | I6: Nairobi | J6: 2014 | K6: 16300 | L6: 0.125 | M6: =O6/(2025-F6) -> 56.405138 | N6: =K6-O6 -> 15171.897 | O6: =K6*(1-L6)^(2025-F6) -> 1128.1028 | R6: Ephy Nafuna | S6: Good
A7: Office Desk | B7: GOK | C7: N/A | D7: NGOB/01/0075 | E7: L-Shaped W/S 1.8 m | F7: 2005 | H7: Nairobi | I7: Nairobi | J7: 2014 | K7: 16300 | L7: 0.125 | M7: =O7/(2025-F7) -> 56.405138 | N7: =K7-O7 -> 15171.897 | O7: =K7*(1-L7)^(2025-F7) -> 1128.1028 | R7: Carolyne Nyambura | S7: Good
A8: Office Desk | B8: GOK | C8: N/A | D8: NGOB/01/0500 | E8: L-Shaped W/S 1.8 m | F8: 2005 | H8: Nairobi | I8: Nairobi | J8: 2014 | K8: 16300 | L8: 0.125 | M8: =O8/(2025-F8) -> 56.405138 | N8: =K8-O8 -> 15171.897 | O8: =K8*(1-L8)^(2025-F8) -> 1128.1028 | R8: Bernadette Nzomo | S8: Good
A9: Office Desk | B9: GOK | C9: N/A | D9: NGOB/01/0493 | E9: L-Shaped W/S 1.8 m | F9: 2005 | H9: Nairobi | I9: Nairobi | J9: 2014 | K9: 16300 | L9: 0.125 | M9: =O9/(2025-F9) -> 56.405138 | N9: =K9-O9 -> 15171.897 | O9: =K9*(1-L9)^(2025-F9) -> 1128.1028 | R9: Stephen Monyoncho | S9: Good
A10: Office Desk | B10: GOK | C10: N/A | D10: NGOB/01/0018 | E10: L-Shaped W/S 1.8 m | F10: 2005 | H10: Nairobi | I10: Nairobi | J10: 2014 | K10: 16300 | L10: 0.125 | M10: =O10/(2025-F10) -> 56.405138 | N10: =K10-O10 -> 15171.897 | O10: =K10*(1-L10)^(2025-F10) -> 1128.1028 | R10: Margaret Mwai | S10: Good
A11: Mobile Drawers | B11: GOK | C11: N/A | D11: NGOB/01/0343 | E11: Four drawers | F11: 2005 | H11: Nairobi | I11: Nairobi | J11: 2014 | K11: 9100 | L11: 0.125 | M11: =O11/(2025-F11) -> 31.489985 | N11: =K11-O11 -> 8470.2003 | O11: =K11*(1-L11)^(2025-F11) -> 629.7997 | R11: Joyce Naisiala | S11: Good
A12: Mobile Drawers | B12: GOK | C12: N/A | D12: NGOB/01/0266 | E12: Four drawers | F12: 2005 | H12: Nairobi | I12: Nairobi | J12: 2014 | K12: 9100 | L12: 0.125 | M12: =O12/(2025-F12) -> 31.489985 | N12: =K12-O12 -> 8470.2003 | O12: =K12*(1-L12)^(2025-F12) -> 629.7997 | R12: Lindon Otieno | S12: Good
A13: Mobile Drawers | B13: GOK | C13: N/A | D13: NGOB/01/0116 | E13: Four drawers | F13: 2005 | H13: Nairobi | I13: Nairobi | J13: 2014 | K13: 9100 | L13: 0.125 | M13: =O13/(2025-F13) -> 31.489985 | N13: =K13-O13 -> 8470.2003 | O13: =K13*(1-L13)^(2025-F13) -> 629.7997 | R13: Aisha Mohammed | S13: Good
... A27: Suspension Drawers | B27: GOK | C27: N/A | D27: NGOB/01/0126 | E27: 3 drawer pedestrial | F27: 2005 | H27: Nairobi | I27: Nairobi | J27: 2014 | K27: 5880 | L27: 0.125 | M27: =O27/(2025-F27) -> 20.347375 | N27: =K27-O27 -> 5473.0525 | O27: =K27*(1-L27)^(2025-F27) -> 406.9475 | R27: Beatrice Topisa | S27: Good
A28: Suspension Drawers | B28: GOK | D28: NGOB/01/0272 | E28: 3 drawer pedestrial | F28: 2005 | H28: Nairobi | I28: Nairobi | J28: 2014 | K28: 5880 | L28: 0.125 | M28: =O28/(2025-F28) -> 20.347375 | N28: =K28-O28 -> 5473.0525 | O28: =K28*(1-L28)^(2025-F28) -> 406.9475 | R28: Mercy Soy | S28: Good
A29: Suspension Drawers | B29: GOK | D29: NGOB/01/0291 | E29: 3 drawer pedestrial | F29: 2005 | H29: Nairobi | I29: Nairobi | J29: 2014 | K29: 5880 | L29: 0.125 | M29: =O29/(2025-F29) -> 20.347375 | N29: =K29-O29 -> 5473.0525 | O29: =K29*(1-L29)^(2025-F29) -> 406.9475 | R29: Elizabeth Kamau | S29: Good
A30: Side Return | B30: GOK | C30: N/A | D30: NGOB/01/0049 | E30: Side return | F30: 2005 | H30: Nairobi | I30: Nairobi | J30: 2014 | K30: 8120 | L30: 0.125 | M30: =O30/(2025-F30) -> 28.098756 | N30: =K30-O30 -> 7558.0249 | O30: =K30*(1-L30)^(2025-F30) -> 561.97512 | R30: Andrew Ogombe | S30: Good
A31: Side Return | B31: GOK | C31: N/A | D31: NGOB/01/0110 | E31: Side return | F31: 2005 | H31: Nairobi | I31: Nairobi | J31: 2014 | K31: 8120 | L31: 0.125 | M31: =O31/(2025-F31) -> 28.098756 | N31: =K31-O31 -> 7558.0249 | O31: =K31*(1-L31)^(2025-F31) -> 561.97512 | R31: Margaret Mwai | S31: Good
A32: Side Return | B32: GOK | C32: N/A | D32: NGOB/01/0445 | E32: Side return | F32: 2005 | H32: Nairobi | I32: Nairobi | J32: 2014 | K32: 8120 | L32: 0.125 | M32: =O32/(2025-F32) -> 28.098756 | N32: =K32-O32 -> 7558.0249 | O32: =K32*(1-L32)^(2025-F32) -> 561.97512 | R32: Charles Mugo | S32: Good
A33: Side Return | B33: GOK | C33: N/A | D33: NGOB/01/0097 | E33: Side return | F33: 2005 | H33: Nairobi | I33: Nairobi | J33: 2014 | K33: 8120 | L33: 0.125 | M33: =O33/(2025-F33) -> 28.098756 | N33: =K33-O33 -> 7558.0249 | O33: =K33*(1-L33)^(2025-F33) -> 561.97512 | R33: Charles Mugo | S33: Good
A34: Side Return | B34: GOK | C34: N/A | D34: NGOB/01/0346 | E34: Side return | F34: 2005 | H34: Nairobi | I34: Nairobi | J34: 2014 | K34: 8120 | L34: 0.125 | M34: =O34/(2025-F34) -> 28.098756 | N34: =K34-O34 -> 7558.0249 | O34: =K34*(1-L34)^(2025-F34) -> 561.97512 | R34: Joyce Naisiala | S34: Good
A35: Side Return | B35: GOK | C35: N/A | D35: N/A | E35: Side return | F35: 2005 | H35: Nairobi | I35: Nairobi | J35: 2014 | K35: 8120 | L35: 0.125 | M35: =O35/(2025-F35) -> 28.098756 | N35: =K35-O35 -> 7558.0249 | O35: =K35*(1-L35)^(2025-F35) -> 561.97512 | R35: Administration department | S35: Good
A36: Side Return | B36: GOK | C36: N/A | D36: N/A | E36: Side return | F36: 2005 | H36: Nairobi | I36: Nairobi | J36: 2014 | K36: 8120 | L36: 0.125 | M36: =O36/(2025-F36) -> 28.098756 | N36: =K36-O36 -> 7558.0249 | O36: =K36*(1-L36)^(2025-F36) -> 561.97512 | R36: Administration department | S36: Good
A37: Desktop Screen | B37: GOK | C37: N/A | D37: N/A | E37: Desktop Screen | F37: 2005 | H37: Nairobi | I37: Nairobi | J37: 2014 | K37: 4060 | L37: 0.125 | M37: =O37/(2025-F37) -> 14.049378 | N37: =K37-O37 -> 3779.0124 | O37: =K37*(1-L37)^(2025-F37) -> 280.98756 | R37: Administration department | S37: Good
A38: Desktop Screen | B38: GOK | C38: N/A | D38: N/A | E38: Desktop Screen | F38: 2005 | H38: Nairobi | I38: Nairobi | J38: 2014 | K38: 4060 | L38: 0.125 | M38: =O38/(2025-F38) -> 14.049378 | N38: =K38-O38 -> 3779.0124 | O38: =K38*(1-L38)^(2025-F38) -> 280.98756 | R38: Administration department | S38: Good
A39: L shape work station | B39: GOK | C39: N/A | D39: NGOB/01/0396 | E39: L shape work station | F39: 2005 | H39: Nairobi | I39: Nairobi | J39: 2014 | K39: 14350 | L39: 0.125 | M39: =O39/(2025-F39) -> 49.657284 | N39: =K39-O39 -> 13356.854 | O39: =K39*(1-L39)^(2025-F39) -> 993.14569 | R39: Berly Odete | S39: Good
A40: L shape work station | B40: GOK | C40: N/A | D40: NGOB/01/0377 | E40: L shape work station | F40: 2005 | H40: Nairobi | I40: Nairobi | J40: 2014 | K40: 14350 | L40: 0.125 | M40: =O40/(2025-F40) -> 49.657284 | N40: =K40-O40 -> 13356.854 | O40: =K40*(1-L40)^(2025-F40) -> 993.14569 | R40: Aisha Mohammed | S40: Good
A41: L shape work station | B41: GOK | C41: N/A | D41: NGOB/01/0350 | E41: L shape work station | F41: 2005 | H41: Nairobi | I41: Nairobi | J41: 2014 | K41: 14350 | L41: 0.125 | M41: =O41/(2025-F41) -> 49.657284 | N41: =K41-O41 -> 13356.854 | O41: =K41*(1-L41)^(2025-F41) -> 993.14569 | R41: Mukhtar Mohamed
A42: L shape work station | B42: GOK | C42: N/A | D42: NGOB/01/0359 | E42: L shape work station | F42: 2005 | H42: Nairobi | I42: Nairobi | J42: 2014 | K42: 14350 | L42: 0.125 | M42: =O42/(2025-F42) -> 49.657284 | N42: =K42-O42 -> 13356.854 | O42: =K42*(1-L42)^(2025-F42) -> 993.14569 | R42: Easther Letting | S42: Good
A43: L shape work station | B43: GOK | C43: N/A | D43: NGOB/01/0351 | E43: L shape work station | F43: 2005 | H43: Nairobi | I43: Nairobi | J43: 2014 | K43: 14350 | L43: 0.125 | M43: =O43/(2025-F43) -> 49.657284 | N43: =K43-O43 -> 13356.854 | O43: =K43*(1-L43)^(2025-F43) -> 993.14569 | R43: Allan Gashoka | S43: Good
A44: L shape work station | B44: GOK | C44: N/A | D44: NGOB/01/0271 | E44: L shape work station | F44: 2005 | H44: Nairobi | I44: Nairobi | J44: 2014 | K44: 14350 | L44: 0.125 | M44: =O44/(2025-F44) -> 49.657284 | N44: =K44-O44 -> 13356.854 | O44: =K44*(1-L44)^(2025-F44) -> 993.14569 | R44: Mercy Soy | S44: Good
A45: L shape work station | B45: GOK | C45: N/A | D45: NGOB/01/0398 | E45: L shape work station | F45: 2005 | H45: Nairobi | I45: Nairobi | J45: 2014 | K45: 14350 | L45: 0.125 | M45: =O45/(2025-F45) -> 49.657284 | N45: =K45-O45 -> 13356.854 | O45: =K45*(1-L45)^(2025-F45) -> 993.14569 | R45: Beatrice Topisa | S45: Good
A46: L shape work station | B46: GOK | C46: N/A | D46: NGOB/01/0382 | E46: L shape work station | F46: 2005 | H46: Nairobi | I46: Nairobi | J46: 2014 | K46: 14350 | L46: 0.125 | M46: =O46/(2025-F46) -> 49.657284 | N46: =K46-O46 -> 13356.854 | O46: =K46*(1-L46)^(2025-F46) -> 993.14569 | R46: Juliet Karari | S46: Good
A47: L shape work station | B47: GOK | C47: N/A | D47: NGOB/01/0326 | E47: L shape work station | F47: 2005 | H47: Nairobi | I47: Nairobi | J47: 2014 | K47: 14350 | L47: 0.125 | M47: =O47/(2025-F47) -> 49.657284 | N47: =K47-O47 -> 13356.854 | O47: =K47*(1-L47)^(2025-F47) -> 993.14569 | R47: Dorris Muthini | S47: Good
A48: Pedestrial mobile | B48: GOK | C48: N/A | D48: NGOB/01/0131 | E48: Four drawers | F48: 2005 | H48: Nairobi | I48: Nairobi | J48: 2014 | K48: 9100 | L48: 0.125 | M48: =O48/(2025-F48) -> 31.489985 | N48: =K48-O48 -> 8470.2003 | O48: =K48*(1-L48)^(2025-F48) -> 629.7997 | R48: Ezna Moriasi | S48: Good
A49: Pedestrial mobile | B49: GOK | C49: N/A | D49: NGOB/01/0121 | E49: Four drawers | F49: 2005 | H49: Nairobi | I49: Nairobi | J49: 2014 | K49: 9100 | L49: 0.125 | M49: =O49/(2025-F49) -> 31.489985 | N49: =K49-O49 -> 8470.2003 | O49: =K49*(1-L49)^(2025-F49) -> 629.7997 | R49: Eric Wainaina | S49: Good
A50: Pedestrial mobile | B50: GOK | C50: N/A | D50: NGOB/01/0111 | E50: Four drawers | F50: 2005 | H50: Nairobi | I50: Nairobi | J50: 2014 | K50: 9100 | L50: 0.125 | M50: =O50/(2025-F50) -> 31.489985 | N50: =K50-O50 -> 8470.2003 | O50: =K50*(1-L50)^(2025-F50) -> 629.7997 | R50: Stephen Kamande | S50: Good
A51: Pedestrial mobile | B51: GOK | C51: N/A | D51: NGOB/01/0494 | E51: Four drawers | F51: 2005 | H51: Nairobi | I51: Nairobi | J51: 2014 | K51: 9100 | L51: 0.125 | M51: =O51/(2025-F51) -> 31.489985 | N51: =K51-O51 -> 8470.2003 | O51: =K51*(1-L51)^(2025-F51) -> 629.7997 | R51: Stephen Monyoncho | S51: Good
A52: Office Chairs | B52: GOK | C52: N/A | D52: NGOB/01/0329 | E52: High back swivel | F52: 2005 | H52: Nairobi | I52: Nairobi | J52: 2014 | K52: 6790 | L52: 0.125 | M52: =O52/(2025-F52) -> 23.496374 | N52: =K52-O52 -> 6320.0725 | O52: =K52*(1-L52)^(2025-F52) -> 469.92747 | R52: Dorris Muthini | S52: Good
A53: Office Chairs | B53: GOK | C53: N/A | D53: NGOB/01/0390 | E53: High back swivel | F53: 2005 | H53: Nairobi | I53: Nairobi | J53: 2014 | K53: 6790 | L53: 0.125 | M53: =O53/(2025-F53) -> 23.496374 | N53: =K53-O53 -> 6320.0725 | O53: =K53*(1-L53)^(2025-F53) -> 469.92747 | R53: Satra Hassan | S53: Good
... A85: Burkley | B85: GOK | C85: N/A | D85: NGOB/01/0363 | E85: Burkley | F85: 2005 | H85: Nairobi | I85: Nairobi | J85: 2014 | K85: 2100 | L85: 0.125 | M85: =O85/(2025-F85) -> 7.2669197 | N85: =K85-O85 -> 1954.6616 | O85: =K85*(1-L85)^(2025-F85) -> 145.33839 | R85: Muktar Mohammed | S85: Good
A86: Burkley | B86: GOK | D86: NGOB/01/0304 | E86: Burkley | F86: 2005 | H86: Nairobi | I86: Nairobi | J86: 2014 | K86: 2100 | L86: 0.125 | M86: =O86/(2025-F86) -> 7.2669197 | N86: =K86-O86 -> 1954.6616 | O86: =K86*(1-L86)^(2025-F86) -> 145.33839 | R86: Juliet Karari | S86: Good
A87: Conneting Unit | B87: GOK | C87: N/A | D87: NGOB/01/538 | E87: Connecting unit | F87: 2005 | H87: Nairobi | I87: Nairobi | J87: 2014 | K87: 21474 | L87: 0.125 | M87: =O87/(2025-F87) -> 74.309444 | N87: =K87-O87 -> 19987.811 | O87: =K87*(1-L87)^(2025-F87) -> 1486.1889 | R87: Andrew Ogombe | S87: Good
A88: Side Cabinet | B88: GOK | C88: N/A | D88: NGOB/01/0414 | E88: Side cabinet | F88: 2005 | H88: Nairobi | I88: Nairobi | J88: 2014 | K88: 14200 | L88: 0.125 | M88: =O88/(2025-F88) -> 49.138219 | N88: =K88-O88 -> 13217.236 | O88: =K88*(1-L88)^(2025-F88) -> 982.76437 | R88: David Njane | S88: Good
A89: Computer desk | B89: GOK | C89: N/A | D89: NGOB/01/0070 | E89: computer desk | F89: 2005 | H89: Nairobi | I89: Nairobi | J89: 2014 | K89: 15700 | L89: 0.125 | M89: =O89/(2025-F89) -> 54.328876 | N89: =K89-O89 -> 14613.422 | O89: =K89*(1-L89)^(2025-F89) -> 1086.5775 | R89: David Njane | S89: Good
A90: Computer desk | B90: GOK | C90: N/A | D90: NGOB/01/0264 | E90: computer desk | F90: 2005 | H90: Nairobi | I90: Nairobi | J90: 2014 | K90: 15700 | L90: 0.125 | M90: =O90/(2025-F90) -> 54.328876 | N90: =K90-O90 -> 14613.422 | O90: =K90*(1-L90)^(2025-F90) -> 1086.5775 | R90: Lindon Otieno | S90: Good
A91: Computer desk | B91: GOK | C91: N/A | D91: NGOB/01/0488 | E91: computer desk | F91: 2005 | H91: Nairobi | I91: Nairobi | J91: 2014 | K91: 15700 | L91: 0.125 | M91: =O91/(2025-F91) -> 54.328876 | N91: =K91-O91 -> 14613.422 | O91: =K91*(1-L91)^(2025-F91) -> 1086.5775 | R91: Bernard Bwoma | S91: Good
A92: Computer desk | B92: GOK | C92: N/A | D92: NGOB/01/0318 | E92: computer desk | F92: 2005 | H92: Nairobi | I92: Nairobi | J92: 2014 | K92: 15700 | L92: 0.125 | M92: =O92/(2025-F92) -> 54.328876 | N92: =K92-O92 -> 14613.422 | O92: =K92*(1-L92)^(2025-F92) -> 1086.5775 | R92: Maureen Kimunguyi | S92: Good
A93: Computer desk | B93: GOK | C93: N/A | D93: NGOB/01/0338 | E93: computer desk | F93: 2005 | H93: Nairobi | I93: Nairobi | J93: 2014 | K93: 15700 | L93: 0.125 | M93: =O93/(2025-F93) -> 54.328876 | N93: =K93-O93 -> 14613.422 | O93: =K93*(1-L93)^(2025-F93) -> 1086.5775 | R93: Procurement ( Intern) | S93: Good
A94: Computer desk | B94: GOK | C94: N/A | D94: NGOB/01/0122 | E94: computer desk | F94: 2005 | H94: Nairobi | I94: Nairobi | J94: 2014 | K94: 15700 | L94: 0.125 | M94: =O94/(2025-F94) -> 54.328876 | N94: =K94-O94 -> 14613.422 | O94: =K94*(1-L94)^(2025-F94) -> 1086.5775 | R94: Satra Hassan | S94: Good
A95: Computer desk | B95: GOK | C95: N/A | D95: NGOB/01/0155 | E95: computer desk with suspended drawers | F95: 2005 | H95: Nairobi | I95: Nairobi | J95: 2014 | K95: 15700 | L95: 0.125 | M95: =O95/(2025-F95) -> 54.328876 | N95: =K95-O95 -> 14613.422 | O95: =K95*(1-L95)^(2025-F95) -> 1086.5775 | R95: Scholastica Mutua | S95: Good
A96: Computer desk | B96: GOK | C96: N/A | D96: NGOB/01/0153 | E96: computer desk | F96: 2005 | H96: Nairobi | I96: Nairobi | J96: 2014 | K96: 15700 | L96: 0.125 | M96: =O96/(2025-F96) -> 54.328876 | N96: =K96-O96 -> 14613.422 | O96: =K96*(1-L96)^(2025-F96) -> 1086.5775 | R96: Richard Chesos | S96: Good
A97: Computer desk | B97: GOK | C97: N/A | D97: NGOB/01/0114 | E97: computer desk | F97: 2005 | H97: Nairobi | I97: Nairobi | J97: 2014 | K97: 15700 | L97: 0.125 | M97: =O97/(2025-F97) -> 54.328876 | N97: =K97-O97 -> 14613.422 | O97: =K97*(1-L97)^(2025-F97) -> 1086.5775 | R97: Yvonne Wangui | S97: Good
A98: Extension Unit | B98: GOK | C98: N/A | D98: NGOB/01/0210 | E98: Extension unit | F98: 2005 | H98: Nairobi | I98: Nairobi | J98: 2014 | K98: 9020 | L98: 0.125 | M98: =O98/(2025-F98) -> 31.21315 | N98: =K98-O98 -> 8395.737 | O98: =K98*(1-L98)^(2025-F98) -> 624.263 | R98: David Njane | S98: Good
... A112: Visitors Chair | B112: GOK | C112: N/A | D112: NGOB/01/0283 | E112: Staking chair blue | F112: 2005 | H112: Nairobi | I112: Nairobi | J112: 2014 | K112: 5104 | L112: 0.125 | M112: =O112/(2025-F112) -> 17.662075 | N112: =K112-O112 -> 4750.7585 | O112: =K112*(1-L112)^(2025-F112) -> 353.2415 | R112: Maureen Kimunguyi | S112: Good
A113: Executive chair | B113: GOK | C113: N/A | D113: NGOB/01/0046 | E113: Conference desk | F113: 2005 | H113: Nairobi | I113: Nairobi | J113: 2014 | K113: 47775 | L113: 0.125 | M113: =O113/(2025-F113) -> 165.32242 | N113: =K113-O113 -> 44468.552 | O113: =K113*(1-L113)^(2025-F113) -> 3306.4485 | R113: Andrew Ogombe
A114: Executive chair | B114: GOK | C114: N/A | D114: NGOB/01/0251 | E114: Cantilever | F114: 2005 | H114: Nairobi | I114: Nairobi | J114: 2014 | K114: 6000 | L114: 0.125 | M114: =O114/(2025-F114) -> 20.762628 | N114: =K114-O114 -> 5584.7474 | O114: =K114*(1-L114)^(2025-F114) -> 415.25255 | R114: Andrew Ogombe
A115: Executive chair | B115: GOK | C115: N/A | D115: NGOB/01/0411 | E115: Cantilever | F115: 2005 | H115: Nairobi | I115: Nairobi | J115: 2014 | K115: 6000 | L115: 0.125 | M115: =O115/(2025-F115) -> 20.762628 | N115: =K115-O115 -> 5584.7474 | O115: =K115*(1-L115)^(2025-F115) -> 415.25255 | R115: Andrew Ogombe
A116: Executive chair | B116: GOK | C116: N/A | D116: NGOB/01/0412 | E116: Cantilever | F116: 2005 | H116: Nairobi | I116: Nairobi | J116: 2014 | K116: 6000 | L116: 0.125 | M116: =O116/(2025-F116) -> 20.762628 | N116: =K116-O116 -> 5584.7474 | O116: =K116*(1-L116)^(2025-F116) -> 415.25255 | R116: Andrew Ogombe
A117: Executive chair | B117: GOK | C117: N/A | D117: NGOB/01/0413 | E117: Cantilever | F117: 2005 | H117: Nairobi | I117: Nairobi | J117: 2014 | K117: 6000 | L117: 0.125 | M117: =O117/(2025-F117) -> 20.762628 | N117: =K117-O117 -> 5584.7474 | O117: =K117*(1-L117)^(2025-F117) -> 415.25255 | R117: Andrew Ogombe
A118: Executive chair | B118: GOK | C118: N/A | D118: NGOB/01/0060 | E118: Cantilever | F118: 2005 | H118: Nairobi | I118: Nairobi | J118: 2014 | K118: 6000 | L118: 0.125 | M118: =O118/(2025-F118) -> 20.762628 | N118: =K118-O118 -> 5584.7474 | O118: =K118*(1-L118)^(2025-F118) -> 415.25255 | R118: Andrew Ogombe
A119: Executive chair | B119: GOK | C119: N/A | D119: NGOB/01/0410 | E119: Cantilever | F119: 2005 | H119: Nairobi | I119: Nairobi | J119: 2014 | K119: 6000 | L119: 0.125 | M119: =O119/(2025-F119) -> 20.762628 | N119: =K119-O119 -> 5584.7474 | O119: =K119*(1-L119)^(2025-F119) -> 415.25255 | R119: Andrew Ogombe
A120: Executive chair | B120: GOK | C120: N/A | D120: NGOB/01/0008 | E120: Cantilever | F120: 2005 | H120: Nairobi | I120: Nairobi | J120: 2014 | K120: 6000 | L120: 0.125 | M120: =O120/(2025-F120) -> 20.762628 | N120: =K120-O120 -> 5584.7474 | O120: =K120*(1-L120)^(2025-F120) -> 415.25255 | R120: Brian Aure
A121: Executive chair | B121: GOK | C121: N/A | D121: NGOB/01/0248 | E121: High back swivel chair | F121: 2005 | H121: Nairobi | I121: Nairobi | J121: 2014 | K121: 7275 | L121: 0.125 | M121: =O121/(2025-F121) -> 25.174686 | N121: =K121-O121 -> 6771.5063 | O121: =K121*(1-L121)^(2025-F121) -> 503.49372 | R121: Andrew Ogombe
A122: Executive chair | B122: GOK | C122: N/A | D122: NGOB/01/0355 | E122: Executive chair | F122: 2004 | H122: Nairobi | I122: Nairobi | J122: 2013 | K122: 28768 | L122: 0.125 | M122: =K122*L122 -> 3596 | N122: =K122-O122 -> 27025.877 | O122: =K122*(1-L122)^(2025-F122) -> 1742.1229 | R122: David Njane
A123: Executive chair | B123: GOK | C123: N/A | D123: NGOB/01/0270 | E123: Executive chair | F123: 2004 | H123: Nairobi | I123: Nairobi | J123: 2013 | K123: 28768 | L123: 0.125 | M123: =K123*L123 -> 3596 | N123: =K123-O123 -> 27025.877 | O123: =K123*(1-L123)^(2025-F123) -> 1742.1229 | R123: Lindon Otieno
A124: Executive chair | B124: GOK | C124: N/A | D124: NGOB/01/0441 | E124: Executive chair | F124: 2004 | H124: Nairobi | I124: Nairobi | J124: 2013 | K124: 28768 | L124: 0.125 | M124: =K124*L124 -> 3596 | N124: =K124-O124 -> 27025.877 | O124: =K124*(1-L124)^(2025-F124) -> 1742.1229 | R124: Stephen Kamande
A125: Office Furniture | B125: GOK | C125: N/A | D125: NGOB/01/0399 | E125: Swing filing cabinet | F125: 2005 | H125: Nairobi | I125: Nairobi | J125: 2014 | K125: 15624 | L125: 0.125 | M125: =K125*L125 -> 1953 | N125: =K125-O125 -> 14542.682 | O125: =K125*(1-L125)^(2025-F125) -> 1081.3176 | R125: Beatrice Topisa
A126: Office Furniture | B126: GOK | C126: N/A | D126: NGOB/01/0332 | E126: filing cabinet with glass | F126: 2005 | H126: Nairobi | I126: Nairobi | J126: 2014 | K126: 22456 | L126: 0.125 | M126: =K126*L126 -> 2807 | N126: =K126-O126 -> 20901.848 | O126: =K126*(1-L126)^(2025-F126) -> 1554.1519 | R126: Dorris Muthini
A127: Office Furniture | B127: GOK | C127: N/A | D127: N/A | E127: oblong coffee table 1.2M | F127: 2005 | H127: Nairobi | I127: Nairobi | J127: 2014 | K127: 8050 | L127: 0.125 | M127: =K127*L127 -> 1006.25 | N127: =K127-O127 -> 7492.8695 | O127: =K127*(1-L127)^(2025-F127) -> 557.13051
A128: Office Furniture | B128: GOK | C128: N/A | D128: NGOB/01/0310 | E128: Filling cabinet glass swing door | F128: 2005 | H128: Nairobi | I128: Nairobi | J128: 2014 | K128: 19600 | L128: 0.125 | M128: =K128*L128 -> 2450 | N128: =K128-O128 -> 18243.508 | O128: =K128*(1-L128)^(2025-F128) -> 1356.4917 | R128: Berly Odete
A129: Office Furniture | B129: GOK | C129: N/A | D129: NGOB/01/0311 | E129: Filling cabinet glass swing door | F129: 2005 | H129: Nairobi | I129: Nairobi | J129: 2014 | K129: 19600 | L129: 0.125 | M129: =K129*L129 -> 2450 | N129: =K129-O129 -> 18243.508 | O129: =K129*(1-L129)^(2025-F129) -> 1356.4917 | R129: Berly Odete
A130: Office Furniture | D130: NGOB/01/0299 | E130: Filling cabinet glass swing door | F130: 2005 | H130: Nairobi | I130: Nairobi | J130: 2014 | K130: 19600 | L130: 0.125 | M130: =K130*L130 -> 2450 | N130: =K130-O130 -> 18243.508 | O130: =K130*(1-L130)^(2025-F130) -> 1356.4917 | R130: Richard Chesos
A131: Office Furniture | B131: GOK | C131: N/A | D131: NGOB/01/0265 | E131: Filling cabinet glass swing door | F131: 2005 | H131: Nairobi | I131: Nairobi | J131: 2014 | K131: 19600 | L131: 0.125 | M131: =K131*L131 -> 2450 | N131: =K131-O131 -> 18243.508 | O131: =K131*(1-L131)^(2025-F131) -> 1356.4917 | R131: Lindon Otieno
A132: Office Furniture | B132: GOK | C132: N/A | D132: NGOB/01/0285 | E132: Swing filing cabinet | F132: 2006 | H132: Nairobi | I132: Nairobi | J132: 2015 | K132: 16800 | L132: 0.125 | M132: =K132*L132 -> 2100 | N132: =K132-O132 -> 15471.192 | O132: =K132*(1-L132)^(2025-F132) -> 1328.8082 | R132: Lindon Otieno
A133: Office Furniture | B133: GOK | C133: N/A | D133: NGOB/01/0416 | E133: Swing filing cabinet | F133: 2006 | H133: Nairobi | I133: Nairobi | J133: 2015 | K133: 16800 | L133: 0.125 | M133: =K133*L133 -> 2100 | N133: =K133-O133 -> 15471.192 | O133: =K133*(1-L133)^(2025-F133) -> 1328.8082 | R133: Francis Tumuti
A134: Office Furniture | B134: GOK | C134: N/A | D134: NGOB/01/0078 | E134: Swing filing cabinet | F134: 2006 | H134: Nairobi | I134: Nairobi | J134: 2015 | K134: 16800 | L134: 0.125 | M134: =K134*L134 -> 2100 | N134: =K134-O134 -> 15471.192 | O134: =K134*(1-L134)^(2025-F134) -> 1328.8082 | R134: Finance Office
A135: Office Furniture | B135: GOK | C135: N/A | D135: NGOB/01/0021 | E135: Filling cabinet | F135: 2006 | H135: Nairobi | I135: Nairobi | J135: 2015 | K135: 11200 | L135: 0.125 | M135: =K135*L135 -> 1400 | N135: =K135-O135 -> 10314.128 | O135: =K135*(1-L135)^(2025-F135) -> 885.87211 | R135: Margaret Mwai
A136: Office Furniture | B136: GOK | C136: N/A | D136: NGOB/01/0022 | E136: Filling cabinet | F136: 2006 | H136: Nairobi | I136: Nairobi | J136: 2015 | K136: 11200 | L136: 0.125 | M136: =K136*L136 -> 1400 | N136: =K136-O136 -> 10314.128 | O136: =K136*(1-L136)^(2025-F136) -> 885.87211 | R136: Margaret Mwai
A137: Office Furniture | D137: NGOB/01/0330 | E137: Filling cabinet | F137: 2006 | H137: Nairobi | I137: Nairobi | J137: 2015 | K137: 11200 | L137: 0.125 | M137: =K137*L137 -> 1400 | N137: =K137-O137 -> 10314.128 | O137: =K137*(1-L137)^(2025-F137) -> 885.87211 | R137: Doris Muthini
A138: Office Furniture | B138: GOK | D138: NGOB/01/0336 | E138: Filling cabinet metalic | F138: 2006 | H138: Nairobi | I138: Nairobi | J138: 2015 | K138: 11200 | L138: 0.125 | M138: =K138*L138 -> 1400 | N138: =K138-O138 -> 10314.128 | O138: =K138*(1-L138)^(2025-F138) -> 885.87211 | R138: Arasa Mokua
A139: Office Furniture | B139: GOK | C139: N/A | D139: NGOB/01/0344 | E139: Square coffee table | F139: 2006 | H139: Nairobi | I139: Nairobi | J139: 2016 | K139: 3240 | L139: 0.125 | M139: =K139*L139 -> 405 | N139: =K139-O139 -> 2983.7299 | O139: =K139*(1-L139)^(2025-F139) -> 256.27015 | R139: Joyce Naisiala
A140: Office Furniture | B140: GOK | C140: N/A | D140: NGOB/01/0328 | E140: Square coffee table | F140: 2006 | H140: Nairobi | I140: Nairobi | J140: 2016 | K140: 3240 | L140: 0.125 | M140: =K140*L140 -> 405 | N140: =K140-O140 -> 2983.7299 | O140: =K140*(1-L140)^(2025-F140) -> 256.27015 | R140: Dorris Muthini
A141: Office Furniture | B141: GOK | C141: N/A | D141: NGOB/01/0510 | E141: Filling cabinet-open | F141: 2006 | H141: Nairobi | I141: Nairobi | J141: 2016 | K141: 11700 | L141: 0.125 | M141: =K141*L141 -> 1462.5 | N141: =K141-O141 -> 10774.58 | O141: =K141*(1-L141)^(2025-F141) -> 925.41997 | R141: Resource Centre
A142: Office Furniture | B142: GOK | C142: N/A | D142: NGOB/01/0511 | E142: Filling cabinet-open | F142: 2006 | H142: Nairobi | I142: Nairobi | J142: 2016 | K142: 11700 | L142: 0.125 | M142: =K142*L142 -> 1462.5 | N142: =K142-O142 -> 10774.58 | O142: =K142*(1-L142)^(2025-F142) -> 925.41997 | R142: Resource Centre
A143: Office Furniture | B143: GOK | C143: N/A | D143: NGOB/01/0512 | E143: Filling cabinet-open | F143: 2006 | H143: Nairobi | I143: Nairobi | J143: 2016 | K143: 11700 | L143: 0.125 | M143: =K143*L143 -> 1462.5 | N143: =K143-O143 -> 10774.58 | O143: =K143*(1-L143)^(2025-F143) -> 925.41997 | R143: Resource Centre
A144: Office Furniture | B144: GOK | C144: N/A | D144: NGOB/01/0513 | E144: Filling cabinet-open | F144: 2006 | H144: Nairobi | I144: Nairobi | J144: 2016 | K144: 11700 | L144: 0.125 | M144: =K144*L144 -> 1462.5 | N144: =K144-O144 -> 10774.58 | O144: =K144*(1-L144)^(2025-F144) -> 925.41997 | R144: Resource Centre
A145: Office Furniture | B145: GOK | C145: N/A | D145: NGOB/01/0514 | E145: Filling cabinet-open | F145: 2006 | H145: Nairobi | I145: Nairobi | J145: 2016 | K145: 11700 | L145: 0.125 | M145: =K145*L145 -> 1462.5 | N145: =K145-O145 -> 10774.58 | O145: =K145*(1-L145)^(2025-F145) -> 925.41997 | R145: Resource Centre
A146: Office Furniture | B146: GOK | C146: N/A | D146: NGOB/01/0482 | E146: Desk panel legged 0.9M | F146: 2006 | H146: Nairobi | I146: Nairobi | J146: 2016 | K146: 4680 | L146: 0.125 | M146: =K146*L146 -> 585 | N146: =K146-O146 -> 4309.832 | O146: =K146*(1-L146)^(2025-F146) -> 370.16799 | R146: Assistant Administartion Manager
A147: Office Furniture | B147: GOK | C147: N/A | D147: NGOB/01/0146 | E147: Desk panel legged 0.9M | F147: 2006 | H147: Nairobi | I147: Nairobi | J147: 2016 | K147: 4680 | L147: 0.125 | M147: =K147*L147 -> 585 | N147: =K147-O147 -> 4309.832 | O147: =K147*(1-L147)^(2025-F147) -> 370.16799 | R147: Assistant Administartion Manager
A148: Office Furniture | B148: GOK | C148: N/A | D148: NGOB/01/0325 | E148: T.V/Photocopier stand | F148: 2006 | H148: Nairobi | I148: Nairobi | J148: 2016 | K148: 10740 | L148: 0.125 | M148: =K148*L148 -> 1342.5 | N148: =K148-O148 -> 9890.5119 | O148: =K148*(1-L148)^(2025-F148) -> 849.48808 | R148: Mercy Soy
A149: Office Furniture | C149: N/A | D149: NGOB/01/0053 | E149: filing cabinet half glass | F149: 2006 | H149: Nairobi | I149: Nairobi | J149: 2016 | K149: 11700 | L149: 0.125 | M149: =K149*L149 -> 1462.5 | N149: =K149-O149 -> 10774.58 | O149: =K149*(1-L149)^(2025-F149) -> 925.41997 | R149: Andrew Ogombe
A150: Office Furniture | B150: GOK | C150: N/A | D150: NGOB/01/0134 | E150: filing cabinet half glass | F150: 2006 | H150: Nairobi | I150: Nairobi | J150: 2016 | K150: 11700 | L150: 0.125 | M150: =K150*L150 -> 1462.5 | N150: =K150-O150 -> 10774.58 | O150: =K150*(1-L150)^(2025-F150) -> 925.41997 | R150: Stephen Monyoncho
A151: Office Furniture | B151: GOK | C151: N/A | D151: NGOB/01/0066 | E151: filing cabinet half glass | F151: 2006 | H151: Nairobi | I151: Nairobi | J151: 2016 | K151: 11700 | L151: 0.125 | M151: =K151*L151 -> 1462.5 | N151: =K151-O151 -> 10774.58 | O151: =K151*(1-L151)^(2025-F151) -> 925.41997 | R151: Bernadette Nzomo
A152: Office Furniture | B152: GOK | C152: N/A | D152: NGOB/01/0079 | E152: filing cabinet open | F152: 2006 | H152: Nairobi | I152: Nairobi | J152: 2016 | K152: 11700 | L152: 0.125 | M152: =K152*L152 -> 1462.5 | N152: =K152-O152 -> 10774.58 | O152: =K152*(1-L152)^(2025-F152) -> 925.41997 | R152: David Njane
A153: Office Furniture | B153: GOK | D153: N/A | E153: Milano two seater | F153: 2006 | H153: Nairobi | I153: Nairobi | J153: 2016 | K153: 14040 | L153: 0.125 | M153: =K153*L153 -> 1755 | N153: =K153-O153 -> 12929.496 | O153: =K153*(1-L153)^(2025-F153) -> 1110.504 | R153: Assistant Administartion Manager
A154: Office desk | B154: GOK | C154: N/A | D154: NGOB/01/0376 | E154: L-shape W/S 1.4 | F154: 2006 | G154: N/A | H154: Nairobi | I154: Nairobi | J154: 2014 | K154: 10850 | L154: 0.125 | M154: =K154*L154 -> 1356.25 | N154: =K154-O154 -> 9991.8114 | O154: =K154*(1-L154)^(2025-F154) -> 858.18861 | R154: Duncan Mokaya | S154: Good
A155: Office desk | B155: GOK | C155: N/A | D155: NGOB/01/0112 | E155: L -shape W/S 1.4m | F155: 2006 | G155: N/A | H155: Nairobi | I155: Nairobi | J155: 2014 | K155: 10850 | L155: 0.125 | M155: =K155*L155 -> 1356.25 | N155: =K155-O155 -> 9991.8114 | O155: =K155*(1-L155)^(2025-F155) -> 858.18861 | R155: Charles Mugo | S155: Good
A156: Office desk | B156: GOK | C156: N/A | D156: NGOB/01/0107 | E156: L-shape W/S 1.4 | F156: 2006 | G156: N/A | H156: Nairobi | I156: Nairobi | J156: 2014 | K156: 10850 | L156: 0.125 | M156: =K156*L156 -> 1356.25 | N156: =K156-O156 -> 9991.8114 | O156: =K156*(1-L156)^(2025-F156) -> 858.18861 | R156: Judy Njiru | S156: Good
A157: Office desk | B157: GOK | D157: NGOB/01/0359 | E157: L-shape W/S 1.4 | F157: 2006 | H157: Nairobi | I157: Nairobi | J157: 2029 | K157: 62900 | L157: 0.125 | M157: =K157*L157 -> 7862.5 | N157: =K157-O157 -> 57924.879 | O157: =K157*(1-L157)^(2025-F157) -> 4975.1211 | R157: Easther Letting | S157: Good
...

Sheet Plant &Machinery Register
A1: Plant & Machinery
B2: Asset Description | C2: Financed by/ source of funds | D2: Serial number | E2: Tag number | F2: Make & Model | G2: Date of Delivery / installation | H2: PV number | I2: Original Location | J2: Current Location | K2: Replacement Date (if applicable) | L2: Purchase amount | M2: Depreciation rate | N2: Annual depreciation | O2: Accumulated depreciation | P2: Net Book Value | Q2: Date of disposal | R2: Disposal value | S2: Responsible officer | T2: Asset condition | U2: Notes
A3: 1 | B3: None | C3: None | D3: None | E3: None | F3: None | G3: None | H3: None | I3: None | J3: None | K3: None | L3: None | M3: None | N3: None | O3: None | P3: None | Q3: None | R3: None | S3: None | T3: None | U3: None | V3: None | W3: None | X3: None | Y3: None | Z3: None
A4: 2
A5: 3
A6: 4
A7: 5
A8: 6
A9: 7
A10: 8
A11: 9
A14: Prepared by: Doris Muthini Designation: Manager SCM Date: 30th June 2025
A15: Checked by: David NjaneDesignation: Finance Manager Date: 30th June 2025
A16: Authorized by: Dr. Laxmana P. Kiptoo Designation: Director/Chief Executive Officer Date: 30th June 2025

Sheet Portable &attractive Items 
A1: Portable &attractive items
B2: Asset Description | C2: Financed by/ source of funds | D2: Serial number | E2: Tag number | F2: Make & Model | G2: Date of Delivery / installation | H2: PV number | I2: Original Location | J2: Current Location | K2: Replacement Date (if applicable) | L2: Purchase amount | M2: Depreciation rate | N2: Annual depreciation | O2: Accumulated depreciation | P2: Net Book Value | Q2: Date of disposal | R2: Disposal value | S2: Responsible officer | T2: Asset condition | U2: Notes
A3: 1 | B3: None | C3: None | D3: None | E3: None | F3: None | G3: None | H3: None | I3: None | J3: None | K3: None | L3: None | M3: None | N3: None | O3: None | P3: None | Q3: None | R3: None | S3: None | T3: None | U3: None | V3: None | W3: None | X3: None | Y3: None | Z3: None
A4: 2
A5: 3
A6: 4
A7: 5
A8: 6
A9: 7
A10: 8
A11: 9
A14: Prepared by: Doris Muthini Designation: Manager SCM Date: 30th June 2025
A15: Checked by: David NjaneDesignation: Finance Manager Date: 30th June 2025
A16: Authorized by: Dr. Laxmana P. Kiptoo Designation: Director/Chief Executive Officer Date: 30th June 2025

Sheet Intangible Asset Register 
A1: Intangible Assets Register
B2: Asset description/ Nature of asset | C2: Document of ownership | D2: Acquired from | E2: Cost/ Fair value | F2: Useful life | G2: Annual depreciation/armotisation | H2: Accumulated depreciation/armotisation | I2: Net Book value | J2: Remarks
A3: 1 | B3: Eset Antivirus | C3: PBORA-Key | D3: Comtech Limited | E3: 268534.2 | F3: One Year | G3: N/A | H3: N/A | I3: 100317.04
A4: 2 | B4: Google Emails | C4: Contract | D4: Cloud IT Limited | E4: 1265432.4 | F4: One Year | G4: N/A | H4: N/A | I4: 822960
A5: 3 | B5: Internet | C5: Contract | D5: Dimension Data Solutions (E.A) Limited | E5: 2095586.4 | F5: One Year | G5: N/A | H5: N/A | I5: 1932096
A6: 4 | I6: =SUM(I3:I5) -> 2855373
A7: 5 | B7: TOTAL
A8: 6
A9: 7
A10: 8
A11: 9
A13: Prepared by: Yvonne Gitau Designation: ICT Officer Date: 30th June 2025
A14: Checked by: Francis Tumuti Designation: Principal ICT Officer Date:30th June 2025
A15: Authorized by: Dr. Laxmana P. Kiptoo Designation: Director/Chief Executive Officer Date: 30th June 2025

Sheet Stocks Consumables Register 
A1: Stocks/ Consumables Register
A2: Description of inventory item | B2: Unit e.g piece, Kgs, etc. | C2: Quantity | D2: Unit+E3:F22 cost | E2: Total Cost | F2: Responsible officer | G2: Remarks
A3: Box File | B3: PIECES | C3: 230 | D3: 350 | E3: 80500 | F3: Arasa Mokuah | G3: Closing stocks as at 30TH JUNE2025
A4: Coloured photocopying Papers Blue | B4: PIECES | C4: 50 | D4: 1650 | E4: 82500 | F4: Arasa Mokuah | G4: Closing stocks as at 30TH JUNE2025
A5: Coloured photocopying Papers Pink | B5: PIECES | C5: 25 | D5: 1679 | E5: 41975 | F5: Arasa Mokuah | G5: Closing stocks as at 30TH JUNE2025
A6: Document folder | B6: PIECES | C6: 1256 | D6: 65 | E6: 81640 | F6: Arasa Mokuah | G6: Closing stocks as at 30TH JUNE2025
A7: ENEVELOPES A4 | B7: PIECES | C7: 350 | D7: 14 | E7: 4900 | F7: Arasa Mokuah | G7: Closing stocks as at 30TH JUNE2025
A8: ENVELOPES A5 | B8: PIECES | C8: 1000 | D8: 5 | E8: 5000 | F8: Arasa Mokuah | G8: Closing stocks as at 30TH JUNE2025
A9: COPY CAT TONER NO 2501 | B9: PIECES | C9: 5 | D9: 5035 | E9: 25175 | F9: Arasa Mokuah | G9: Closing stocks as at 30TH JUNE2025
A10: GLUE PASTE | B10: DOZENS | C10: 6 | D10: 3328.8 | E10: 19972.8 | F10: Arasa Mokuah | G10: Closing stocks as at 30TH JUNE2025
A11: PAPER PUNCH | B11: PIECES | C11: 5 | D11: 1600 | E11: 8000 | F11: Arasa Mokuah | G11: Closing stocks as at 30TH JUNE2025
A12: GLOBE SPRING FILE | B12: BOX | C12: 18 | D12: 11050 | E12: 198900 | F12: Arasa Mokuah | G12: Closing stocks as at 30TH JUNE2025
A13: PHOTOCOPYING PAPERS | B13: PIECES | C13: 220 | D13: 1195 | E13: 262900 | F13: Arasa Mokuah | G13: Closing stocks as at 30TH JUNE2025
A14: REGISTRATION FORMS(Form 2) | B14: REAMS | C14: 6 | D14: 4700 | E14: 28200 | F14: Arasa Mokuah | G14: Closing stocks as at 30TH JUNE2025
... A24: TONER NO 411 | B24: PIECES | C24: 1 | D24: 30250 | E24: 30250 | F24: Arasa Mokuah | G24: Closing stocks as at 30TH JUNE2025
A25: TONER NO 412 | B25: PIECES | C25: 1 | D25: 30250 | E25: =D25 -> 30250 | F25: Arasa Mokuah | G25: Closing stocks as at 30TH JUNE2025
A26: TONER NO 413 | B26: PIECES | C26: 1 | D26: 30250 | E26: =D26 -> 30250 | F26: Arasa Mokuah | G26: Closing stocks as at 30TH JUNE2025
A27: TONER NO TK-475 | B27: PIECES | C27: 4 | D27: 10000 | E27: 40000 | F27: Arasa Mokuah | G27: Closing stocks as at 30TH JUNE2025
A28: TONER NO1160 | B28: PIECES | C28: 4 | D28: 7000 | E28: 28000 | F28: Arasa Mokuah | G28: Closing stocks as at 30TH JUNE2025
A29: STAPLERS PINS | B29: PACKETS | C29: 3 | D29: 1350 | E29: 4050 | F29: Arasa Mokuah | G29: Closing stocks as at 30TH JUNE2025
A30: HIGHLIGHTERS | B30: DOZENS | C30: 33 | D30: 900 | E30: 29700 | F30: Arasa Mokuah | G30: Closing stocks as at 30TH JUNE2025
A31: STICKY NOTES | B31: DOZENS | C31: 36 | D31: 670 | E31: 24120 | F31: Arasa Mokuah | G31: Closing stocks as at 30TH JUNE2025
A32: MASKING TAPES | B32: PIECES | C32: 24 | D32: 195 | E32: 4680 | F32: Arasa Mokuah | G32: Closing stocks as at 30TH JUNE2025
A33: STAPLERS | B33: PIECES | C33: 1 | D33: 1350 | E33: 1350 | F33: Arasa Mokuah | G33: Closing stocks as at 30TH JUNE2025
A34: BIC BIROS | B34: PACKETS | C34: 20 | D34: 560 | E34: 11200 | F34: Arasa Mokuah | G34: Closing stocks as at 30TH JUNE2025
A35: TOTALS | E35: =SUM(E3:E34) -> 1553162.8
A38: Prepared by: Arasa Mokuah Designation: SCM Officer Date: 30th June 2025
A39: Checked by: Doris Muthini Designation: Manager SCM Date: 30th June 2025
A40: Authorized by: Dr. Laxmana P. Kiptoo Designation: Director/Chief Executive Officer Date: 30th June 2025

Sheet Railway register 
A1: Railways Register
B2: Railway description | C2: Railway ID | D2: Length (Kms) | E2: Date of commissioning | F2: Type of rail | G2: Amenities available | H2: Land registry ID | I2: Useful life | J2: Cost | K2: Annual depreciation | L2: Accumulated depreciation | M2: Net Book value | N2: Remarks
A3: 1 | B3: None | C3: None | D3: None | E3: None | F3: None | G3: None | H3: None | I3: None | J3: None | K3: None | L3: None | M3: None | N3: None
A4: 2
A5: 3
A6: 4
A7: 5
A8: 6
A9: 7
A10: 8
A11: 9
A13: Prepared by: Doris Muthini Designation: Manager SCM Date: 30th June 2025
A14: Checked by: David NjaneDesignation: Finance Manager Date: 30th June 2025
A15: Authorized by: Dr. Laxmana P. Kiptoo Designation: Director/Chief Executive Officer Date: 30th June 2025

Sheet Roads Infastructure register 
A1: Roads Infrastructure Register
B2: Road description | C2: Road ID | D2: Length (Kms) | E2: Date of commissioning | F2: Type of road e.g. bitumen, earth etc. | G2: Class of road e.g. A,B,C,D etc. | H2: Mode of funding e.g PPP, GoK, external funding etc. | I2: Amenities available | J2: Land registry ID | K2: Useful life | L2: Cost | M2: Annual depreciation | N2: Accumulated depreciation | O2: Net Book value | P2: Remarks
A3: 1 | B3: None | C3: None | D3: None | E3: None | F3: None | G3: None | H3: None | I3: None | J3: None | K3: None | L3: None | M3: None | N3: None | O3: None | P3: None
A4: 2
A5: 3
A6: 4
A7: 5
A8: 6
A11: Prepared by: Doris Muthini Designation: Manager SCM Date: 30th June 2025
A12: Checked by: David NjaneDesignation: Finance Manager Date: 30th June 2025
A13: Authorized by: Dr. Laxmana P. Kiptoo Designation: Director/Chief Executive Officer Date: 30th June 2025

Sheet Other Infastructure register 
A1: Other Infrastructure Register
B2: Asset Description | C2: Financed by/ source of funds | D2: Length (if applicable) | E2: Size (e.g. area, production capacity etc.) | F2: Make & Model | G2: Date installation/ Commissioning | H2: PV number | I2: Original Location | J2: Current Location | K2: Installation amount | L2: Depreciation rate | M2: Annual depreciation | N2: Accumulated depreciation | O2: Net Book Value | P2: Date of disposal | Q2: Disposal value | R2: Responsible officer | S2: Asset condition | T2: Notes
A3: 1 | B3: None | C3: None | D3: None | E3: None | F3: None | G3: None | H3: None | I3: None | J3: None | K3: None | L3: None | M3: None | N3: None | O3: None | P3: None | Q3: None | R3: None | S3: None | T3: None
A4: 2
A5: 3
A6: 4
A7: 5
A8: 6
A9: 7
A12: Prepared by: Doris Muthini Designation: Manager SCM Date: 30th June 2025
A13: Checked by: David NjaneDesignation: Finance Manager Date: 30th June 2025
A14: Authorized by: Dr. Laxmana P. Kiptoo Designation: Director/Chief Executive Officer Date: 30th June 2025

Sheet Biological register 
A1: Biological Assets Register
B2: Asset description | C2: Category of asset | D2: Unit of measurement (Pieces, acreage etc) | E2: Quantity | F2: Unit cost | G2: Total Cost | H2: Fair value | I2: Useful life of the assets | J2: Annual depreciation | K2: Accumulated depreciation | L2: Net Book value | M2: Remarks
A3: 1 | B3: None | C3: None | D3: None | E3: None | F3: None | G3: None | H3: None | I3: None | J3: None | K3: None | L3: None | M3: None
A4: 2
A5: 3
A6: 4
A9: Prepared by: Doris Muthini Designation: Manager SCM Date: 30th June 2025
A10: Checked by: David NjaneDesignation: Finance Manager Date: 30th June 2025
A11: Authorized by: Dr. Laxmana P. Kiptoo Designation: Director/Chief Executive Officer Date: 30th June 2025

Sheet Subsoil register 
A1: Subsoil Assets Register
B2: Asset description | C2: Mineral type (Diamond, gold, copper etc) | D2: Unit of measurement (Pieces, acreage etc) | E2: Quantity | H2: Monetary value | K2: Useful life of the assets | L2: Annual depreciation | M2: Accumulated depreciation | N2: Net Book value | O2: Remarks
E3: Opening quantity | F3: Additions | G3: Closing quantities | H3: Opening balance | I3: Additions | J3: Closing balance
A4: 1 | B4: None | C4: None | D4: None | E4: None | F4: None | G4: None | H4: None | I4: None | J4: None | K4: None | L4: None | M4: None | N4: None | O4: None
A5: 2
A6: 3
A7: 4
A8: 5
A9: 6
A12: Prepared by: Doris Muthini Designation: Manager SCM Date: 30th June 2025
A13: Checked by: David NjaneDesignation: Finance Manager Date: 30th June 2025
A14: Authorized by: Dr. Laxmana P. Kiptoo Designation: Director/Chief Executive Officer Date: 30th June 2025

Sheet Major maintenance register 
A1: Major Maintenance Register
B2: Asset | C2: Asset Category | D2: Location of asset | E2: Start Date | F2: Expected date of completion | G2: Amount spent to date | H2: Date of transfer to asset category | I2: Amount transferred to asset category | J2: Amount expensed
A3: 1 | B3: None | C3: None | D3: None | E3: None | F3: None | G3: None | H3: None | I3: None | J3: None
A4: 2
A5: 3
A6: 4
A7: 5
A8: 6
A9: 7
A10: 8
A11: 9
A12: 10
A14: Prepared by: Doris Muthini Designation: Manager SCM Date: 30th June 2025
A15: Checked by: David NjaneDesignation: Finance Manager Date: 30th June 2025
A16: Authorized by: Dr. Laxmana P. Kiptoo Designation: Director/Chief Executive Officer Date: 30th June 2025

Sheet Work in progress register 
A1: Work In Progress Register
B2: Asset Category | C2: Location of asset | D2: Start Date | E2: Expected date of completion | F2: Percentage of completion | G2: Amount spent to date | H2: Commitment in next financial year | I2: Commitment beyond next financial year | J2: Class of assets transferred to | K2: Date of transfer | L2: Amount of WIP transferred | M2: Balance of WIP
A3: 1 | B3: None | C3: None | D3: None | E3: None | F3: None | G3: None | H3: None | I3: None | J3: None | K3: None | L3: None | M3: None
A4: 2
A5: 3
A6: 4
A7: 5
A8: 6
A9: 7
A10: 8
A11: 9
A14: Prepared by: Doris Muthini Designation: Manager SCM Date: 30th June 2025
A15: Checked by: David NjaneDesignation: Finance Manager Date: 30th June 2025
A16: Authorized by: Dr. Laxmana P. Kiptoo Designation: Director/Chief Executive Officer Date: 30th June 2025

Sheet Investments register 
A1: Investments Register (For Investments Other Than Investment Property)
B2: Nature/ type of investments | C2: Institution investment held | D2: Document of ownership | E2: Source of funds | F2: Date of investment | G2: Maturity date | H2: Term/ duration of investment | I2: Interest rate applicable to the investment | J2: Quantity | K2: Unit Cost | L2: Initial cost of purchase | M2: Expected interest due on maturity | N2: Maturity value | O2: Name and signature of the officer or employee placing the investment | P2: Remarks
A3: 1 | B3: None | C3: None | D3: None | E3: None | F3: None | G3: None | H3: None | I3: None | J3: None | K3: None | L3: None | M3: None | N3: None | O3: None | P3: None
A4: 2
A5: 3
A6: 4
A7: 5
A8: 6
A11: Prepared by: Doris Muthini Designation: Manager SCM Date: 30th June 2025
A12: Checked by: David NjaneDesignation: Finance Manager Date: 30th June 2025
A13: Authorized by: Dr. Laxmana P. Kiptoo Designation: Director/Chief Executive Officer Date: 30th June 2025

Sheet Cash register 
A1: Cash Register
B2: Type of float/ Description | C2: Currency | D2: Source of Funds | E2: Responsible officer | F2: Balance Kshs | G2: Comments
A3: 1 | B3: None | C3: None | D3: None | E3: None | F3: None | G3: We don’t handle cash
A4: 2
A5: 3
A6: 4
A7: 5
A8: 6
A11: Prepared by: Mohamed Muktar Designation: Principal Finance Officer Date: 30th June 2025
A12: Checked by: David Njane Designation: Finance Manager Date: 30th June 2025
A13: Authorized by: Dr. Laxmana P. Kiptoo Designation: Director/Chief Executive Officer Date:30th June 2025

Sheet Bank register 
A1: Bank Register
B2: Account name | C2: Account Number | D2: Currency | E2: Type of Account e.g. fixed, current, savings etc. | F2: Name of Bank | G2: Source of Funds | H2: Bank signatories | I2: Balance Kshs | J2: Notes
A3: 1 | B3: PUBLIC BENEFIT ORGANIZATIONS REGULATORY AUTHORITY | C3: 01136030582100 | D3: Kes | E3: executive Current | F3: Co-operative bank | G3: G.O.K | H3: Executive Director, Director of Operations and Finance Manager | I3: 1592283
A4: 2 | B4: PUBLIC BENEFIT ORGANIZATIONS REGULATORY AUTHORITY | C4: 01136030582101 | D4: Kes | E4: project account | F4: Co-operative bank | G4: Collaborations | H4: Executive Director, Director of Operations and Finance Manager | I4: 120463
A5: 3 | B5: PUBLIC BENEFIT ORGANIZATIONS REGULATORY AUTHORITY | C5: 01136030582102 | D5: Kes | E5: revenue account | F5: Co-operative bank | G5: Internally Genereted | H5: Executive Director, Director of Operations and Finance Manager | I5: 12119
A6: 4 | B6: PUBLIC BENEFIT ORGANIZATIONS REGULATORY AUTHORITY | C6: 1770279085801 | D6: Kes | E6: Current | F6: Equity Bank | G6: G.O.K | H6: Executive Director, Director of Operations and Finance Manager | I6: 113456
A7: 5 | B7: PUBLIC BENEFIT ORGANIZATIONS REGULATORY AUTHORITY | C7: 0051095178002 | D7: Kes | E7: Current | F7: SBM Bank | G7: G.O.K | H7: Executive Director, Director of Operations and Finance Manager | I7: 121610
A8: 6 | I8: =SUM(I3:I7) -> 1959931
A9: 7
A13: Prepared by: Mohamed Muktar Designation: Principal Finance Officer Date: 30th June 2025
A14: Checked by: David Njane Designation: Finance Manager Date: 30th June 2025
A15: Authorized by: Dr. Laxmana P. Kiptoo Designation: Director/Chief Executive Officer Date:30th June 2025

Sheet Loans receivables register
A1: Loans Receivable Register
B2: Entity lent | C2: Location of the loan agreement or other supporting documentation, for example, the file | D2: Effective date of lending | E2: Maturity date | F2: Loan duration | G2: Purpose of loan | H2: Interest rate (%) | I2: Currency of lending | J2: Conversion Rate | K2: Amount lent in original currency | L2: Amount lent in Kshs | M2: Actual amounts disbursed to date Kshs | N2: Interest receivable Kshs | O2: Other charges Kshs | P2: Total receivable Kshs | Q2: Amount Repaid Kshs | R2: Amount Outstanding Kshs | S2: Comments
A3: 1 | B3: None | C3: None | D3: None | E3: None | F3: None | G3: None | H3: None | I3: None | J3: None | K3: None | L3: None | M3: None | N3: None | O3: None | P3: None | Q3: None | R3: None | S3: None
A4: 2
A5: 3
A6: 4
A7: 5
A8: 6
A11: Prepared by: Mohamed Muktar Designation: Principal Finance Officer Date: 30th June 2025
A12: Checked by: David Njane Designation: Finance Manager Date: 30th June 2025
A13: Authorized by: Dr. Laxmana P. Kiptoo Designation: Director/Chief Executive Officer Date:30th June 2025

Sheet Accounts receivables register 
A1: Accounts Receivables Register
B2: Name of Customer | C2: Items supplied | D2: Department supplied | E2: Responsible officer | F2: Currency | G2: Amount receivable Kshs | H2: Due date of receipt | I2: Number of days outstanding | J2: Remarks
A3: 1 | B3: None | C3: None | D3: None | E3: None | F3: None | G3: None | H3: None | I3: None | J3: None
A4: 2
A5: 3
A6: 4
A7: 5
A8: 6
A9: 7
A11: Prepared by: Mohamed Muktar Designation: Principal Finance Officer Date: 30th June 2025
A12: Checked by: David Njane Designation: Finance Manager Date: 30th June 2025
A13: Authorized by: Dr. Laxmana P. Kiptoo Designation: Director/Chief Executive Officer Date:30th June 2025

Sheet Other receivables register 
A1: Other Receivables Register
B2: Nature of receivable | C2: Name of Customer | D2: Staff Personal number (where applicable) | E2: Department | F2: Responsible officer | G2: Currency | H2: Amount receivable Kshs | I2: Due date of receipt | J2: Number of days outstanding | K2: Remarks
A3: 1 | B3: Salary Advance | C3: MR. KIRIMA TONY MUTHURI | D3: Staff Debtor | E3: HR | F3: Dr. Laxmana P.Kiptoo | G3: Kes | H3: 51500 | I3: Monthly Basis | J3: Deducted on monthly Basis
A4: 2 | B4: Salary Advance | C4: MR. KASHOKA NG`ANG`A ALLAN | D4: Staff Debtor | E4: FINANCE | F4: Dr. Laxmana P.Kiptoo | G4: Kes | H4: 15000 | I4: Monthly Basis | J4: Deducted on monthly Basis
A5: 3 | B5: Salary Advance | C5: MR. NJOROGE WAITHAKA ERIC | D5: Staff Debtor | E5: Operation | F5: Dr. Laxmana P.Kiptoo | G5: Kes | H5: 16664 | I5: Monthly Basis | J5: Deducted on monthly Basis
A6: 4 | B6: Salary Advance | C6: MR. LETOLUO SANKALE NICK | D6: Staff Debtor | E6: Operation | F6: Dr. Laxmana P.Kiptoo | G6: Kes | H6: 33331 | I6: Monthly Basis | J6: Deducted on monthly Basis
A7: 5 | B7: Salary Advance | C7: MISS. YIAILE NAISIALA JOYCE | D7: Staff Debtor | E7: Corporate | F7: Dr. Laxmana P.Kiptoo | G7: Kes | H7: 166669 | I7: Monthly Basis | J7: Deducted on monthly Basis
A8: 6 | B8: Salary Advance | C8: MISS. AMBUNDO ISICHI YVONNE | D8: Staff Debtor | E8: RESEARCH | F8: Dr. Laxmana P.Kiptoo | G8: Kes | H8: 48668 | I8: Monthly Basis | J8: Deducted on monthly Basis
A9: 7 | B9: Salary Advance | C9: MR. KIROP CHESOS RICHARD | D9: Staff Debtor | E9: PR | F9: Dr. Laxmana P.Kiptoo | G9: Kes | H9: 136000 | I9: Monthly Basis | J9: Deducted on monthly Basis
A10: 8 | B10: Salary Advance | C10: MR. ABDULLAHI MUKTAR MOHAMED | D10: Staff Debtor | E10: FINANCE | F10: Dr. Laxmana P.Kiptoo | G10: Kes | H10: 75001 | I10: Monthly Basis | J10: Deducted on monthly Basis
A11: 9 | B11: Salary Advance | C11: MRS. ODETE CLAIRE ADERA BERYL | D11: Staff Debtor | E11: HR | F11: Dr. Laxmana P.Kiptoo | G11: Kes | H11: 200000 | I11: Monthly Basis | J11: Deducted on monthly Basis
A12: 10 | B12: Salary Advance | C12: MRS. ACHOLA ANYIRI CATHERINE | D12: Staff Debtor | E12: Operation | F12: Dr. Laxmana P.Kiptoo | G12: Kes | H12: 11375 | I12: Monthly Basis | J12: Deducted on monthly Basis
A13: 11 | B13: Salary Advance | C13: MR. BUYA KOMORA ISRAEL | D13: Staff Debtor | E13: ADMINISTRATION | F13: Dr. Laxmana P.Kiptoo | G13: Kes | H13: 91667 | I13: Monthly Basis | J13: Deducted on monthly Basis
A14: 12 | B14: Salary Advance | C14: MR. CRISPUS MWENDA MUREGA | D14: Staff Debtor | E14: FINANCE | F14: Dr. Laxmana P.Kiptoo | G14: Kes | H14: 41667 | I14: Monthly Basis | J14: Deducted on monthly Basis
A15: 13 | B15: Salary Advance | C15: MISS. OLOO ACHIENG` SARAH | D15: Staff Debtor | E15: Operation | F15: Dr. Laxmana P.Kiptoo | G15: Kes | H15: 18333 | I15: Monthly Basis | J15: Deducted on monthly Basis
H16: =SUM(H3:H15) -> 905875
A17: Prepared by: Mohamed Muktar Designation: Principal Finance Officer Date: 30th June 2025
A18: Checked by: David Njane Designation: Finance Manager Date: 30th June 2025
A19: Authorized by: Dr. Laxmana P. Kiptoo Designation: Director/Chief Executive Officer Date:30th June 2025

Sheet Imprest register 
A1: Imprest Register
B2: Staff name | C2: Staff Personal number | D2: Department | E2: Imprest warrant No. | F2: Date of issue | G2: Expected date of surrender | H2: Actual date of surrender | I2: Number of days outstanding | J2: Currency | K2: Imprest Amount Kshs | L2: Amount surrendered Kshs | M2: Balance Kshs | N2: Remarks
A3: 1 | B3: Mr. Laxmana Peter Kiptoo | E3: IMP933 | F3: 07 Apr 2025 | G3: 24 Apr 2025 | H3: 24 Apr 2025 | I3: 0 | J3: Kes | K3: 468403.2 | L3: 468403.2 | M3: =K3-L3 -> 0
A4: 2 | B4: Mrs. Bernadette Njeri Nzomo | E4: IMP934 | F4: 07 Apr 2025 | G4: 24 Apr 2025 | H4: 24 Apr 2025 | I4: 0 | J4: Kes | K4: 255772.8 | L4: 255772.8 | M4: =K4-L4 -> 0
A5: 3 | B5: Mr. Otieno Nicholas Lindon | E5: IMP915 | F5: 10 Apr 2025 | G5: 14 Apr 2025 | H5: 14 Apr 2025 | I5: 0 | J5: Kes | K5: 28000 | L5: 28000 | M5: =K5-L5 -> 0
A6: 4 | B6: Miss. Soy Cherutoh Mercy | E6: IMP916 | F6: 10 Apr 2025 | G6: 14 Apr 2025 | H6: 14 Apr 2025 | I6: 0 | J6: Kes | K6: 28000 | L6: 28000 | M6: =K6-L6 -> 0
A7: 5 | B7: Mr. Njane Kirubi Robert David | E7: IMP917 | F7: 10 Apr 2025 | G7: 14 Apr 2025 | H7: 14 Apr 2025 | I7: 0 | J7: Kes | K7: 68000 | L7: 68000 | M7: =K7-L7 -> 0
A8: 6 | B8: Mr. Sang Kiplangat Isaiah | E8: IMP918 | F8: 10 Apr 2025 | G8: 14 Apr 2025 | H8: 14 Apr 2025 | I8: 0 | J8: Kes | K8: 33600 | L8: 33600 | M8: =K8-L8 -> 0
A9: 7 | B9: Miss. Muthini Mwende Dorris | E9: IMP919 | F9: 10 Apr 2025 | G9: 14 Apr 2025 | H9: 14 Apr 2025 | I9: 0 | J9: Kes | K9: 28000 | L9: 28000 | M9: =K9-L9 -> 0
A10: 8 | B10: Mr. Otieno Nicholas Lindon | E10: IMP921 | F10: 11 Apr 2025 | G10: 18 Apr 2025 | H10: 18 Apr 2025 | I10: 0 | J10: Kes | K10: 14000 | L10: 14000 | M10: =K10-L10 -> 0
A11: 9 | B11: Mr. Sang Kiplangat Isaiah | E11: IMP922 | F11: 11 Apr 2025 | G11: 18 Apr 2025 | H11: 18 Apr 2025 | I11: 0 | J11: Kes | K11: 27092 | L11: 27092 | M11: =K11-L11 -> 0
A12: 10 | B12: Mr. Njane Kirubi Robert David | E12: IMP923 | F12: 11 Apr 2025 | G12: 18 Apr 2025 | H12: 18 Apr 2025 | I12: 0 | J12: Kes | K12: 14000 | L12: 14000 | M12: =K12-L12 -> 0
A13: 11 | B13: Miss. Muthini Mwende Dorris | E13: IMP924 | F13: 11 Apr 2025 | G13: 18 Apr 2025 | H13: 18 Apr 2025 | I13: 0 | J13: Kes | K13: 21812 | L13: 21812 | M13: =K13-L13 -> 0
A14: 12 | B14: Miss. Soy Cherutoh Mercy | E14: IMP925 | F14: 11 Apr 2025 | G14: 18 Apr 2025 | H14: 18 Apr 2025 | I14: 0 | J14: Kes | K14: 14000 | L14: 14000 | M14: =K14-L14 -> 0
... A55: 53 | B55: Mr. Sang Kiplangat Isaiah | E55: IMP967 | F55: 26 Jun 2025 | G55: 09 Jul 2025 | H55: 09 Jul 2025 | I55: 0 | J55: Kes | K55: 2681000 | L55: 2681000 | M55: =K55-L55 -> 0
K56: =SUM(K3:K55) -> 15152366 | L56: =SUM(L3:L55) -> 15152366
A59: Prepared by: Mohamed Muktar Designation: Principal Finance Officer Date: 30th June 2025
A60: Checked by: David Njane Designation: Finance Manager Date: 30th June 2025
A61: Authorized by: Dr. Laxmana P. Kiptoo Designation: Director/Chief Executive Officer Date:30th June 2025

Sheet Loans payable register 
A1: Loans Payable Register
B2: Source of debt i.e. country/ Institution | C2: Type of funding i.e. foreign or domestic, if foreign bilateral or multilateral | D2: Location of the loan agreement or other supporting documentation, for example, the file | E2: Effective date of borrowing | F2: Maturity date | G2: Loan duration | H2: Purpose of loan | I2: Perceived benefits of the loan | J2: Interest rate (%) | K2: Currency of borrowing | L2: Conversion Rate | M2: Amount borrowed in original currency | N2: Amount borrowed in Kshs | O2: Amounts received to date Kshs | P2: Interest payable Kshs | Q2: Other charges Kshs | R2: Total payable Kshs | S2: Amount Repaid Kshs | T2: Amount Outstanding Kshs | U2: Remarks
A3: 1 | B3: None | C3: None | D3: None | E3: None | F3: None | G3: None | H3: None | I3: None | J3: None | K3: None | L3: None | M3: None | N3: None | O3: None | P3: None | Q3: None | R3: None | S3: None | T3: None | U3: None
A4: 2
A5: 3
A6: 4
A7: 5
A9: Prepared by: Mohamed Muktar Designation: Principal Finance Officer Date: 30th June 2025
A10: Checked by: David Njane Designation: Finance Manager Date: 30th June 2025
A11: Authorized by: Dr. Laxmana P. Kiptoo Designation: Director/Chief Executive Officer Date:30th June 2025

Sheet contigent Liabities register
A1: Contingent Liabilities Register
B2: Nature of contingent liability | C2: Payable to | D2: Currency | E2: Estimated Amount Kshs | F2: Expected date of payment | G2: Remarks
A3: 1 | B3: None | C3: None | D3: None | E3: None | F3: None | G3: None
A4: 2
A5: 3
A6: 4
A7: 5
A8: 6
A9: 7
A12: Prepared by: Mohamed Muktar Designation: Principal Finance Officer Date: 30th June 2025
A13: Checked by: David Njane Designation: Finance Manager Date: 30th June 2025
A14: Authorized by: Dr. Laxmana P. Kiptoo Designation: Director/Chief Executive Officer Date:30th June 2025

Sheet Accruals register 
A1: Accruals/ Provisions Register
B2: Description of accruals or provision | C2: Payable to | D2: Amount Kshs | E2: Due date of payment | F2: Number of days outstanding | G2: Remarks
A3: 1 | B3: ='[1]Accruals register '!B4 -> AOG | C3: ='[1]Accruals register '!C4 -> AUDIT SERVICES | D3: 1879200 | E3: ='[1]Accruals register '!E4 -> Immediate | F3: ='[1]Accruals register '!F4 -> Over 30days | G3: ='[1]Accruals register '!G4 -> 0
D4: =SUM(D3:D3) -> 1879200
A8: Prepared by: Mohamed Muktar Designation: Principal Finance Officer Date: 30th June 2025
A9: Checked by: David Njane Designation: Finance Manager Date: 30th June 2025
A10: Authorized by: Dr. Laxmana P. Kiptoo Designation: Director/Chief Executive Officer Date:30th June 2025

Sheet Accounts payable register 
A1: Accounts Payables Register
B2: Name of Supplier | C2: Items supplied | D2: Department | E2: Responsible officer | F2: Currency | G2: Source of funding | H2: Amount payable Kshs | I2: Due date of payment | J2: Number of days outstanding | K2: Remarks
A3: 1 | B3: AOG | C3: AUDIT SERVICES | E3: CEO | F3: KES | G3: GOK | H3: 1879200
A4: 2 | B4: NW REALITE | C4: RENT-HQ | E4: CEO | F4: KES | G4: GOK | H4: =9956605.72-1500000+5036256.7-2000000-2000000-3000000+5036256.7-5000000 -> 6529119.1
A5: 3 | B5: BRITAM | C5: PENSION | E5: CEO | F5: KES | G5: GOK | H5: 9371154
A6: 4 | B6: KANJAMA | C6: LEGAL | E6: CEO | F6: KES | G6: GOK | H6: 250000
A7: 5 | B7: OTIENO,YOGO,OJURO & CO | C7: LEGAL | E7: CEO | F7: KES | G7: GOK | H7: 557000
A8: 6 | B8: WAMBUGU & MURIUKI ADV | C8: LEGAL | E8: CEO | F8: KES | G8: GOK | H8: 870000
A9: 7 | B9: CHERONO AND KIPTOO ADVOCATES | C9: LEGAL | E9: CEO | F9: KES | G9: GOK | H9: 4069474
A10: 8 | B10: KENYA EXPEORTS PROMOTION & BRANDING AGENCY | C10: LEGAL | E10: CEO | F10: KES | G10: GOK | H10: 3800000
A11: 9 | B11: THE STAR | C11: AVERTISING | E11: CEO | F11: KES | G11: GOK | H11: 467712
A12: 10 | B12: JAMII TELECOM (JTL) | C12: INTERNET | E12: CEO | F12: KES | G12: GOK | H12: 639160.01
A13: 11 | B13: CLOUD IT LTD | C13: Google Mail | E13: CEO | F13: KES | G13: GOK | H13: 336635.76
B14: TOTAL | H14: =SUM(H3:H13) -> 28769455
A16: Prepared by: Mohamed Muktar Designation: Principal Finance Officer Date: 30th June 2025
A17: Checked by: David Njane Designation: Finance Manager Date: 30th June 2025
A18: Authorized by: Dr. Laxmana P. Kiptoo Designation: Director/Chief Executive Officer Date:30th June 2025

Sheet Pensions payable register
A1: Pensions Payable Register
B2: Personal No. | C2: Officer Name | D2: Designation & Job Grade | E2: Department | F2: Date of birth | G2: Date of employment | H2: Date of confirmation | I2: Eligible for pension (Y/N) | J2: Number of complete months | K2: Factor for pension computation | L2: Current annual pay | M2: Pension payable | N2: Ex-gratia payments | O2: Total payment due | P2: Lumpsum payment | Q2: Amount outstanding | R2: Monthly pension payable to officer | S2: Remarks
A3: 1 | B3: None | C3: None | D3: None | E3: None | F3: None | G3: None | H3: None | I3: None | J3: None | K3: None | L3: None | M3: None | N3: None | O3: None | P3: None | Q3: None | R3: None | S3: None
A4: 2
A5: 3
A6: 4
A7: 5
A9: Prepared by: Doris Muthini Designation: Manager SCM Date: 30th June 2025
A10: Checked by: David NjaneDesignation: Finance Manager Date: 30th June 2025
A11: Authorized by: Dr. Laxmana P. Kiptoo Designation: Director/Chief Executive Officer Date: 30th June 2025

Sheet Other liabilities register 
A1: Other Liabilities Register
B2: Nature of liability | C2: Payable to | D2: Department | E2: Responsible officer | F2: Currency | G2: Source of funding | H2: Amount payable Kshs | I2: Due date of payment | J2: Number of days outstanding | K2: Remarks
A3: 1 | B3: None | C3: None | D3: None | E3: None | F3: None | G3: None | H3: None | I3: None | J3: None | K3: None
A4: 2
A5: 3
A6: 4
A7: 5
A8: 6
A9: 7
A11: Prepared by: Doris Muthini Designation: Manager SCM Date: 30th June 2025
A12: Checked by: David NjaneDesignation: Finance Manager Date: 30th June 2025
A13: Authorized by: Dr. Laxmana P. Kiptoo Designation: Director/Chief Executive Officer Date: 30th June 2025

Sheet Asset movement form
A1: Assets Movement Form
B2: Date of movement | C2: Asset description | D2: Asset category | E2: Make/ Model | F2: Serial No. | G2: Old location | H2: New location | I2: Condition | J2: Movement approved by | K2: Remarks
A3: 1 | B3: None | C3: None | D3: None | E3: None | F3: None | G3: None | H3: None | I3: None | J3: None | K3: None
A4: 2
A5: 3
A6: 4
A7: 5
A8: 6
A9: 7
A10: 8
A11: 9
A13: Prepared by: Doris Muthini Designation: Manager SCM Date: 30th June 2025
A14: Checked by: David NjaneDesignation: Finance Manager Date: 30th June 2025
A15: Authorized by: Dr. Laxmana P. Kiptoo Designation: Director/Chief Executive Officer Date: 30th June 2025

Sheet Revaluation Schedule 
A1: Revaluation Schedule
B2: Asset Class | C2: Last Revaluation | D2: Next Revaluation | E2: Remarks
A3: 1 | B3: Land | C3: N/A | D3: N/A | E3: N/A
A4: 2 | B4: Buildings | C4: N/A | D4: N/A | E4: N/A
A5: 3 | B5: Roads & Bridges | C5: N/A | D5: N/A | E5: N/A
A6: 4 | B6: Other infrastructure | C6: N/A | D6: N/A | E6: N/A
A7: 5
A8: 6
A9: 7
A12: Prepared by: Doris Muthini Designation: Manager SCM Date: 30th June 2025
A13: Checked by: David NjaneDesignation: Finance Manager Date: 30th June 2025
A14: Authorized by: Dr. Laxmana P. Kiptoo Designation: Director/Chief Executive Officer Date: 30th June 2025

Sheet Losses Register 
A1: Losses Register
B2: Details of the item lost or written off, for example, asset code, description, value | C2: Statement as to the circumstances of the loss, for example, dates, personnel involved, how the loss occurred | D2: Loss category for example theft, destroyed etc. | E2: Corrective action taken; | F2: General ledger account and cost centre codes; | G2: Preparer’s name and title | H2: Name and title of the approval officer (must have a losses delegation)
A3: 1 | B3: Nil | C3: Nil | D3: Nil | E3: Nil | F3: Nil | G3: Nil | H3: Nil
A4: 2
A5: 3
A6: 4
A7: 5
A8: 6
A10: Prepared by: Doris Muthini Designation: Manager SCM Date: 30th June 2025
A11: Checked by: David NjaneDesignation: Finance Manager Date: 30th June 2025
A12: Authorized by: Dr. Laxmana P. Kiptoo Designation: Director/Chief Executive Officer Date: 30th June 2025

Sheet Guarantees &indeminities 
A1: Guarantees and Indemnities Register
B2: Nature of the document (guarantee or indemnity or both) | C2: Initial amount involved | D2: Extent of the guarantee or indemnity, i.e. extent of liability | E2: Date of normal expiration | F2: Duration of the document | G2: Current amount of the guaranteed instrument, including any accrued interest or reductions in principal and/or interest.
A3: 1 | B3: None | C3: None | D3: None | E3: None | F3: None | G3: None
A4: 2
A5: 3
A6: 4
A7: 5
A8: 6
A12: Prepared by: Doris Muthini Designation: Manager SCM Date: 30th June 2025
A13: Checked by: David NjaneDesignation: Finance Manager Date: 30th June 2025
A14: Authorized by: Dr. Laxmana P. Kiptoo Designation: Director/Chief Executive Officer Date: 30th June 2025

Sheet Lease register 
A1: Lease Register
B3: Description of the leased asset | C3: Lease term/ period | D3: Repayment schedule, including the residual value and balloon payments | E3: Present value of minimum or total lease payments | F3: Type of lease, (operating or finance lease) | G3: Name and address of the lessor | H3: Name of the officer who approved the lease contract | I3: Nominal rate of interest applied in the lease | J3: Location of the lease agreement, for example, file reference and location. | K3: Remarks
A4: 1 | B4: Ofice space, 15th and 14th Floors - Headquarters | C4: Six Years | D4: Quarterly | E4: 4497712 | F4: Operating Lease | G4: Cooperative Bank of Kenya limited P.O Box 30664-00100, Nairobi | H4: Mutuma Nkanata, Executive Director | I4: N/A | J4: Ngos Co-ordination Board, 15th Floor Cooperative Bank House Building
A5: 2 | B5: Office Space - Mombasa Office | C5: Six Years | D5: Quarterly | E5: 188083 | F5: Operating Lease | G5: National Social Security Fund, P.O Box 30599-00100 Nairobi | H5: Mutuma Nkanata, Executive Director | I5: 20% after every two years | J5: Ngos Co-ordination Board, 15th Floor Cooperative Bank House Building
A6: 3
A7: 4
A8: 5
A9: 6
A10: 7
A12: Prepared by: Ephy Nafuna Designation: Senior Administration Officer Date: 30th June 2025
A13: Checked by: Tony Kirima Designation: Human resource and Administration Manager Date: 30th June 2025
A14: Authorized by: Dr. Laxmana P. Kiptoo Designation: Director/Chief Executive Officer Date: 30th June 2025

Sheet Litigation Register 
A1: Litigation Register
B2: File/register number | C2: Insurance reference/claim number (where applicable) | D2: Other party’s name | E2: Other party's legal representative | F2: Brief description of the claim | G2: Departmental officers(s)/ agent(s) involved (where applicable) | H2: Date that the file was created | I2: Commencement date of the action | J2: Date of the service of writs | K2: Departmental legal representative (panel and non-panel) | L2: Action taken to date | M2: Total estimate of the costs, inclusive of legal and damages | N2: Legal costs (amounts, description and date) incurred to date | O2: Any comments, for example, reference to legal opinions received and other pertinent details | P2: Current status of the claim, for example, claim settled. | Q2: Remarks
A3: 1 | B3: JRE05/21 | C3: N/A | D3: IDPS | E3: HELLEN ADV. JR. ORDERS | F3: GOVERNANCE CHALLENGES & ROLE OF THE BOARD | G3: M.SOY | H3: 44197 | I3: 44197 | J3: CONT | K3: M.SOY | L3: COURT ATTENDANCE | M3: 1.5M | N3: 800000 | O3: N/A | P3: APPLICATION HEARING
A4: 2 | B4: HCCC NO.E066 OF 2022 | C4: N/A | D4: ADAN WAKO | E4: SELF | F4: LOSS OF EMPLOYMENT | G4: B.ONDERI | H4: 44713 | I4: 44713 | J4: CONT | K4: B.ONDERI | L4: FILING AND SERVICE | M4: 400000 | N4: N/A | O4: N/A | P4: HEARING PENDING
A5: 3 | B5: ELLLLRC 16/22 | C5: N/A | D5: LINDON OTIENO | E5: MURIUKI & CO. | F5: PEITION ON LABOUR RIGHTS AND CHANGE IN STAFF DESIGNATION | G5: B.ONDERI | H5: 44197 | I5: 44197 | J5: CONT | K5: MURIUKI | L5: COURT ATTENDANCE | M5: 3M | N5: N/A | O5: N/A | P5: JUDGEMENT MADE
A6: 4 | B6: H.C J.R E046 OF 2022 | C6: N/A | D6: VISION FOR LIFE | E6: KENANI & CO. | F6: GOVERNANCE AND LAND DISPUTE | G6: M.SOY | H6: 44682 | I6: 44682 | J6: CONT | K6: M.SOY | L6: FILING AND SERVICE | M6: 200000 | N6: N/A | O6: N/A | P6: RULING PENDING
A7: 5 | B7: KISUMU/CIV//85 OF 2021 | C7: N/A | D7: KDP | E7: YOGO&CO. | F7: FUNDING & GOVERNANCE CHALLENGES | G7: M.SOY | H7: 45403 | I7: 45403 | J7: CONT | K7: M.SOY | L7: COURT ATTENDANCE | M7: 1.8M | N7: 500,00 | O7: N/A | P7: MEDIATION PENDING
A8: 6 | B8: CIVIL CASE/TBA/2024 | C8: TBA | D8: ELIZABETH MAINA | E8: T.B.A | F8: INSURANCE CLAIM BY DOCTRINE OF SUBROGATION | G8: M.SOY | H8: 45600 | I8: T.B.A | J8: CONT. | K8: M.SOY | L8: DRAFTING OF PLEADINGS | M8: 10000 | N8: N/A | O8: N/A | P8: MENTION DATE PENDING
A9: 7 | B9: E.L.R.C NO.E616/2023 | C9: N/A | D9: BERYL ODETE | E9: KENJA&CO. | F9: BREACH OF CONSTITUTIONAL RIGHT TO FAIR LABOUR PRACTICES | G9: M.SOY | H9: 45466 | I9: 45466 | J9: CONT | K9: MURIUKI | L9: FILING AND SERVICE | M9: 3M | N9: N/A | O9: N/A | P9: HEARING 24/9/2024
A10: 8 | B10: HCCHRPET E382/2024 | C10: N/A | D10: KHRC & AFRICOG | E10: KATIBA INST. | F10: CONSTITUTIONAL | G10: M.SOY/VITALIS | H10: 45459 | I10: 45551 | J10: CONT. | K10: MUNYAO MUTHAMA & KASHINDI ADVOCATES | L10: FILING OF SUBMISSIONS | M10: 15000000 | N10: 7000000 | O10: N/A | P10: MENTION 23/07/2024
A11: 9 | B11: HCCHRPET/E519/2024 | C11: N/A | D11: CIVIL SOCIETY REFERENCE GROUP | E11: ARENDE ORIRI & ASSO. ADVOCATES | F11: CONSTITUTIONAL | G11: M. SOY/VITALIS/ A.G | H11: 45723 | I11: 45723 | J11: CONT. | K11: MUNYAO MUTHAMA & KASHINDI ADVOCATES | L11: COURT OF APPEAL, AWAITING EMPANELMENT OF THE BENCH | M11: 20000000 | N11: 10000000 | O11: N/A | P11: JUDGEMENT MADE ON APRIL 30,2025 | Q11: STAY ORDERS GIVEN
M12: =SUM(M3:M11) -> 35610000 | N12: =SUM(N3:N11) -> 17800000
A14: Checked by: Mercy Soy Designation: Senior Legal Officer Date: 30th June 2025
A15: Authorized by: Lindon Nicolas Otieno Designation: Legal Manager Date: 30th June 2025
A16: Authorized by: Dr. Laxmana P. Kiptoo Designation: Director/Chief Executive Officer Date: 30th June 2025

Sheet Equipment sign out register 
A1: Equipment Sign Out Register
B2: Name of the borrower | C2: Contact details of the borrower | D2: Description of the item | E2: Asset or attractive item tag number (where applicable) or loan equipment identifier | F2: Date of loan | G2: Signature of the borrower | H2: Date equipment returned | I2: Remarks
A3: 1 | B3: Nil | C3: Nil | D3: Nil | E3: Nil | F3: Nil | G3: Nil | H3: Nil | I3: Nil
A4: 2
A5: 3
A6: 4
A7: 5
A8: 6
A9: 7
A10: 8
A12: Prepared by: Ephy Nafuna Designation: Senior Administration Officer Date: 30th June 2025
A13: Checked by: Tony Kirima Designation: Human resource and Administration Manager Date: 30th June 2025
A14: Authorized by: Dr. Laxmana P. Kiptoo Designation: Director/Chief Executive Officer Date: 30th June 2025

Sheet Asset transfer form 
A1: Asset Transfer Form
A2: Between units/ departments
B3: Office furniture/ Equipment | D3: IT and Computer Equipment | F3: Current Location and Unit | H3: New Location and Unit | J3: Comments/ reason for the transfer | K3: Signature of transferor (old holder) | L3: Signature of transferee (new holder)
B4: Description of asset | C4: Tag Number | D4: Description of asset | E4: Tag Number | F4: User | G4: Condition | H4: User | I4: Condition
A5: 1 | B5: Nil | C5: Nil | D5: Nil | E5: Nil | F5: Nil | G5: Nil | H5: Nil | I5: Nil | J5: Nil | K5: Nil | L5: Nil
A6: 2
A7: 3
A8: 4
A9: 5
A10: 6
A11: 7
A14: Prepared by: Ephy Nafuna Designation: Senior Administration Officer Date: 30th June 2025
A15: Checked by: Tony Kirima Designation: Human resource and Administration Manager Date: 30th June 2025
A16: Authorized by: Dr. Laxmana P. Kiptoo Designation: Director/Chief Executive Officer Date: 30th June 2025

Sheet Asset Handover form
A1: Asset Handover Form
A2: Name of staff: ____________________________________________
A3: Designation of staff: _______________________________________
A4: Unit/ Department: ____________________________________________________
B5: Asset Description | C5: Asset code | D5: Serial Number | E5: Location | F5: Comments on the condition of the asset
A6: 1 | B6: Nil | C6: Nil | D6: Nil | E6: Nil | F6: Nil
A7: 2
A8: 3
A9: 4
A10: 5
A11: 6
A12: 7
A13: 8
A14: 9
A17: Prepared by: Ephy Nafuna Designation: Senior Administration Officer Date: 30th June 2025
A18: Checked by: Tony Kirima Designation: Human resource and Administration Manager Date: 30th June 2025
A19: Authorized by: Dr. Laxmana P. Kiptoo Designation: Director/Chief Executive Officer Date: 30th June 2025

Sheet Asset reconciliation report 
A1: Asset Reconciliation Report
B2: Category of assets | C2: Opening balances - cost | F2: Opening balances - Accumulated depreciation | I2: Asset additions | L2: Asset disposals | O2: Annual depreciation charge | R2: Impairments | U2: Revaluations | X2: Net Book value
C3: Asset register | D3: Accounting records | E3: Difference | F3: Asset register | G3: Accounting records | H3: Difference | I3: Asset register | J3: Accounting records | K3: Difference | L3: Asset register | M3: Accounting records | N3: Difference | O3: Asset register | P3: Accounting records | Q3: Difference | R3: Asset register | S3: Accounting records | T3: Difference | U3: Asset register | V3: Accounting records | W3: Difference | X3: Asset register | Y3: Accounting records | Z3: Difference
A4: 1 | B4: Motor vehicles | C4: ='Motor Vehicle Register'!M11 -> 57350297 | D4: =C4 -> 57350297 | E4: 0 | F4: ='Motor Vehicle Register'!P11 -> 43740803 | G4: =F4 -> 43740803 | H4: 0 | I4: 0 | J4: 0 | K4: 0 | L4: 0 | M4: 0 | N4: 0 | O4: ='Motor Vehicle Register'!O11 -> 8748160.5 | P4: =O4 -> 8748160.5 | Q4: 0 | R4: 0 | S4: 0 | T4: 0 | U4: 0 | V4: 0 | W4: 0 | X4: ='Motor Vehicle Register'!Q11 -> 13609494 | Y4: =X4 -> 13609494 | Z4: 0
A5: 2 | B5: Furniture & fittings | C5: ='Furniture&Fittings '!K387 -> 20146307 | D5: =C5 -> 20146307 | E5: 0 | F5: ='Furniture&Fittings '!N387 -> 13136345 | G5: =F5 -> 13136345 | H5: 0 | I5: 0 | J5: 0 | K5: 0 | L5: 0 | M5: 0 | N5: 0 | O5: ='Furniture&Fittings '!M387 -> 2380872.6 | P5: =O5 -> 2380872.6 | Q5: 0 | R5: 0 | S5: 0 | T5: 0 | U5: 0 | V5: 0 | W5: 0 | X5: ='[2]Furniture&Fittings '!P462 -> 3.154132e+10 | Y5: =X5 -> 3.154132e+10 | Z5: 0
A6: 3 | B6: office equipment | C6: ='Office equipment register '!O67 -> 14154002 | D6: =C6 -> 14154002 | E6: 0 | F6: ='Office equipment register '!N67 -> 14800395 | G6: =F6 -> 14800395 | H6: 0 | I6: 0 | J6: 0 | K6: 0 | L6: 0 | M6: 0 | N6: 0 | O6: ='Office equipment register '!M67 -> 2733643.1 | P6: =O6 -> 2733643.1 | Q6: 0 | R6: 0 | S6: 0 | T6: 0 | U6: 0 | V6: 0 | W6: 0 | X6: 16176002 | Y6: =X6 -> 16176002 | Z6: 0
A7: 4 | B7: ICT EQUIPMENT | C7: ='ICT Computer Register '!L223 -> 19308410 | D7: =C7 -> 19308410 | F7: ='ICT Computer Register '!O223 -> 15839372 | G7: =F7 -> 15839372 | H7: 0 | I7: 0 | J7: 0 | K7: 0 | L7: 0 | M7: 0 | N7: 0 | O7: ='ICT Computer Register '!N223 -> 2988734 | P7: =O7 -> 2988734 | Q7: 0 | R7: 0 | S7: 0 | T7: 0 | U7: 0 | V7: 0 | W7: 0 | X7: ='ICT Computer Register '!P223 -> 3469038 | Y7: =X7 -> 3469038 | Z7: 0
A9: Prepared by: Doris Muthini Designation: Manager SCM Date: 30th June 2025
A10: Checked by: David NjaneDesignation: Finance Manager Date: 30th June 2025
A11: Authorized by: Dr. Laxmana P. Kiptoo Designation: Director/Chief Executive Officer Date: 30th June 2025
